{
  "atualizado_em": "29/06/2026, 17:25:08",
  "cdi_mensal": 1.109,
  "oportunidades": [
    {
      "Acao": "BBAS",
      "Preco_Atual": 20.34,
      "Preco_Medio": 22.58,
      "Quantidade": 2000,
      "Ticker_Opcao": "BBASG210W4",
      "Estilo": "EUROPEAN",
      "Venc": "2026-07-24",
      "Dias_ate_Venc": 19,
      "Strike": 20.89,
      "Posicao": "OTM",
      "Dist_Strike": "+2.7%",
      "Premio_Bruto": 0.31,
      "IR": 0.0465,
      "Corretagem": 0.0209,
      "Premio_Liquido": 0.2426,
      "Taxa": 1.1928,
      "Taxa_Dia": 0.0628,
      "Taxa_Mes": 1.88,
      "Volume": 5300,
      "Bid_Volume": 100,
      "Sem_Oferta": false,
      "Liquidez": "ALTA",
      "Score": 5.5,
      "CDI": "SUPERA",
      "Tipo": "CALL",
      "Estrategia": "Call Vendida",
      "Ganho_Por_Lote": 24.26,
      "Ganho_Total": 485.22,
      "Lotes_Carteira": 20,
      "Delta": 0.414,
      "Gamma": 0.2973,
      "Theta": -0.018,
      "Vega": 0.0218,
      "Rho": 0.0061,
      "Poe": 38.95,
      "Margin": 0,
      "IV": 20.28,
      "Moneyness": "OTM"
    },
    {
      "Acao": "B3SA",
      "Preco_Atual": 14.83,
      "Preco_Medio": 18.43,
      "Quantidade": 500,
      "Ticker_Opcao": "B3SAG156W4",
      "Estilo": "AMERICAN",
      "Venc": "2026-07-24",
      "Dias_ate_Venc": 19,
      "Strike": 15.46,
      "Posicao": "OTM",
      "Dist_Strike": "+4.2%",
      "Premio_Bruto": 0.36,
      "IR": 0.054,
      "Corretagem": 0.0155,
      "Premio_Liquido": 0.2905,
      "Taxa": 1.9591,
      "Taxa_Dia": 0.1031,
      "Taxa_Mes": 3.09,
      "Volume": 3900,
      "Bid_Volume": 0,
      "Sem_Oferta": true,
      "Liquidez": "ALTA",
      "Score": 5.5,
      "CDI": "SUPERA",
      "Tipo": "CALL",
      "Estrategia": "Call Vendida",
      "Ganho_Por_Lote": 29.05,
      "Ganho_Total": 145.27,
      "Lotes_Carteira": 5,
      "Delta": 0.417,
      "Gamma": 0.2701,
      "Theta": -0.0181,
      "Vega": 0.016,
      "Rho": 0.0044,
      "Poe": 38.01,
      "Margin": 0,
      "IV": 31.84,
      "Moneyness": "OTM"
    },
    {
      "Acao": "CYRE",
      "Preco_Atual": 23.33,
      "Preco_Medio": 26.71,
      "Quantidade": 1000,
      "Ticker_Opcao": "CYRES224W4",
      "Estilo": "EUROPEAN",
      "Venc": "2026-07-24",
      "Dias_ate_Venc": 19,
      "Strike": 22.45,
      "Posicao": "OTM",
      "Dist_Strike": "-3.8%",
      "Premio_Bruto": 0.75,
      "IR": 0.1125,
      "Corretagem": 0.0225,
      "Premio_Liquido": 0.615,
      "Taxa": 2.6363,
      "Taxa_Dia": 0.1388,
      "Taxa_Mes": 4.16,
      "Volume": 100,
      "Bid_Volume": 0,
      "Sem_Oferta": true,
      "Liquidez": "ALTA",
      "Score": 5.5,
      "CDI": "SUPERA",
      "Tipo": "PUT",
      "Estrategia": "Put Vendida",
      "Garantia_Por_Lote": 2245,
      "Lotes_Possiveis": 33,
      "Garantia_Total": 74085,
      "Ganho_Total": 2029.66,
      "Limite_Put": 75000,
      "Pct_Limite_Usado": 98.8,
      "Delta": -0.318,
      "Gamma": 0.1291,
      "Theta": -0.0214,
      "Vega": 0.0228,
      "Rho": -0.006,
      "Poe": 36.09,
      "Margin": 0,
      "IV": 49.32,
      "Moneyness": "OTM"
    },
    {
      "Acao": "ITUB",
      "Preco_Atual": 42.24,
      "Preco_Medio": 44.54,
      "Quantidade": 500,
      "Ticker_Opcao": "ITUBG435W4",
      "Estilo": "EUROPEAN",
      "Venc": "2026-07-24",
      "Dias_ate_Venc": 19,
      "Strike": 43.18,
      "Posicao": "OTM",
      "Dist_Strike": "+2.2%",
      "Premio_Bruto": 0.76,
      "IR": 0.114,
      "Corretagem": 0.0432,
      "Premio_Liquido": 0.6028,
      "Taxa": 1.4271,
      "Taxa_Dia": 0.0751,
      "Taxa_Mes": 2.25,
      "Volume": 100,
      "Bid_Volume": 0,
      "Sem_Oferta": true,
      "Liquidez": "ALTA",
      "Score": 4.5,
      "CDI": "SUPERA",
      "Tipo": "CALL",
      "Estrategia": "Call Vendida",
      "Ganho_Por_Lote": 60.28,
      "Ganho_Total": 301.41,
      "Lotes_Carteira": 5,
      "Delta": 0.43,
      "Gamma": 0.1408,
      "Theta": -0.0385,
      "Vega": 0.0454,
      "Rho": 0.013,
      "Poe": 40.37,
      "Margin": 0,
      "IV": 22.14,
      "Moneyness": "OTM"
    },
    {
      "Acao": "ITUB",
      "Preco_Atual": 42.24,
      "Preco_Medio": 44.54,
      "Quantidade": 500,
      "Ticker_Opcao": "ITUBG437W5",
      "Estilo": "AMERICAN",
      "Venc": "2026-07-31",
      "Dias_ate_Venc": 24,
      "Strike": 43.43,
      "Posicao": "OTM",
      "Dist_Strike": "+2.8%",
      "Premio_Bruto": 0.91,
      "IR": 0.1365,
      "Corretagem": 0.0434,
      "Premio_Liquido": 0.7301,
      "Taxa": 1.7284,
      "Taxa_Dia": 0.072,
      "Taxa_Mes": 2.16,
      "Volume": 6200,
      "Bid_Volume": 0,
      "Sem_Oferta": true,
      "Liquidez": "ALTA",
      "Score": 4.5,
      "CDI": "SUPERA",
      "Tipo": "CALL",
      "Estrategia": "Call Vendida",
      "Ganho_Por_Lote": 73.01,
      "Ganho_Total": 365.04,
      "Lotes_Carteira": 5,
      "Delta": 0.466,
      "Gamma": 0.1258,
      "Theta": -0.0367,
      "Vega": 0.0521,
      "Rho": 0.0178,
      "Poe": 43.66,
      "Margin": 0,
      "IV": 20.82,
      "Moneyness": "OTM"
    },
    {
      "Acao": "CYRE",
      "Preco_Atual": 23.33,
      "Preco_Medio": 26.71,
      "Quantidade": 1000,
      "Ticker_Opcao": "CYREG259W4",
      "Estilo": "AMERICAN",
      "Venc": "2026-07-24",
      "Dias_ate_Venc": 19,
      "Strike": 25.95,
      "Posicao": "OTM",
      "Dist_Strike": "+11.2%",
      "Premio_Bruto": 0.26,
      "IR": 0.039,
      "Corretagem": 0.026,
      "Premio_Liquido": 0.1951,
      "Taxa": 0.836,
      "Taxa_Dia": 0.044,
      "Taxa_Mes": 1.32,
      "Volume": 1200,
      "Bid_Volume": 0,
      "Sem_Oferta": true,
      "Liquidez": "ALTA",
      "Score": 3.5,
      "CDI": "SUPERA",
      "Tipo": "CALL",
      "Estrategia": "Call Vendida",
      "Ganho_Por_Lote": 19.5,
      "Ganho_Total": 195.05,
      "Lotes_Carteira": 10,
      "Delta": 0.212,
      "Gamma": 0.1055,
      "Theta": -0.0235,
      "Vega": 0.0184,
      "Rho": 0.0035,
      "Poe": 17.9,
      "Margin": 0,
      "IV": 40.23,
      "Moneyness": "OTM"
    },
    {
      "Acao": "BBAS",
      "Preco_Atual": 20.34,
      "Preco_Medio": 22.58,
      "Quantidade": 2000,
      "Ticker_Opcao": "BBASG212W4",
      "Estilo": "AMERICAN",
      "Venc": "2026-07-24",
      "Dias_ate_Venc": 19,
      "Strike": 21.14,
      "Posicao": "OTM",
      "Dist_Strike": "+3.9%",
      "Premio_Bruto": 0.22,
      "IR": 0.033,
      "Corretagem": 0.0211,
      "Premio_Liquido": 0.1659,
      "Taxa": 0.8154,
      "Taxa_Dia": 0.0429,
      "Taxa_Mes": 1.29,
      "Volume": 200,
      "Bid_Volume": 0,
      "Sem_Oferta": true,
      "Liquidez": "ALTA",
      "Score": 3.5,
      "CDI": "SUPERA",
      "Tipo": "CALL",
      "Estrategia": "Call Vendida",
      "Ganho_Por_Lote": 16.59,
      "Ganho_Total": 331.72,
      "Lotes_Carteira": 20,
      "Delta": 0.33,
      "Gamma": 0.2771,
      "Theta": -0.0161,
      "Vega": 0.0202,
      "Rho": 0.0048,
      "Poe": 30.73,
      "Margin": 0,
      "IV": 20.73,
      "Moneyness": "OTM"
    },
    {
      "Acao": "ITUB",
      "Preco_Atual": 42.24,
      "Preco_Medio": 44.54,
      "Quantidade": 500,
      "Ticker_Opcao": "ITUBG447W4",
      "Estilo": "AMERICAN",
      "Venc": "2026-07-24",
      "Dias_ate_Venc": 19,
      "Strike": 44.43,
      "Posicao": "OTM",
      "Dist_Strike": "+5.2%",
      "Premio_Bruto": 0.41,
      "IR": 0.0615,
      "Corretagem": 0.0444,
      "Premio_Liquido": 0.3041,
      "Taxa": 0.7199,
      "Taxa_Dia": 0.0379,
      "Taxa_Mes": 1.14,
      "Volume": 1200,
      "Bid_Volume": 0,
      "Sem_Oferta": true,
      "Liquidez": "ALTA",
      "Score": 3.5,
      "CDI": "SUPERA",
      "Tipo": "CALL",
      "Estrategia": "Call Vendida",
      "Ganho_Por_Lote": 30.41,
      "Ganho_Total": 152.03,
      "Lotes_Carteira": 5,
      "Delta": 0.285,
      "Gamma": 0.1213,
      "Theta": -0.0314,
      "Vega": 0.0394,
      "Rho": 0.0087,
      "Poe": 26.26,
      "Margin": 0,
      "IV": 22.33,
      "Moneyness": "OTM"
    },
    {
      "Acao": "BBSE",
      "Preco_Atual": 39.17,
      "Preco_Medio": 35.69,
      "Quantidade": 600,
      "Ticker_Opcao": "BBSES381W4",
      "Estilo": "EUROPEAN",
      "Venc": "2026-07-24",
      "Dias_ate_Venc": 19,
      "Strike": 38.18,
      "Posicao": "OTM",
      "Dist_Strike": "-2.5%",
      "Premio_Bruto": 0.4,
      "IR": 0.06,
      "Corretagem": 0.0382,
      "Premio_Liquido": 0.3018,
      "Taxa": 0.7705,
      "Taxa_Dia": 0.0406,
      "Taxa_Mes": 1.22,
      "Volume": 1500,
      "Bid_Volume": 0,
      "Sem_Oferta": true,
      "Liquidez": "ALTA",
      "Score": 3.5,
      "CDI": "SUPERA",
      "Tipo": "PUT",
      "Estrategia": "Put Vendida",
      "Garantia_Por_Lote": 3818,
      "Lotes_Possiveis": 19,
      "Garantia_Total": 72542,
      "Ganho_Total": 573.46,
      "Limite_Put": 75000,
      "Pct_Limite_Usado": 96.7,
      "Delta": -0.219,
      "Gamma": 0.1563,
      "Theta": -0.0097,
      "Vega": 0.0317,
      "Rho": -0.0066,
      "Poe": 23.33,
      "Margin": 0,
      "IV": 22.24,
      "Moneyness": "OTM"
    }
  ]
}