{
  "atualizado_em": "13/05/2026, 09:00:10",
  "cdi_mensal": 1.1274,
  "oportunidades": [
    {
      "Acao": "CYRE",
      "Preco_Atual": 21.85,
      "Preco_Medio": 26.71,
      "Quantidade": 1000,
      "Ticker_Opcao": "CYREF235",
      "Estilo": "AMERICAN",
      "Venc": "2026-06-19",
      "Dias_ate_Venc": 26,
      "Strike": 23.55,
      "Posicao": "OTM",
      "Dist_Strike": "+7.8%",
      "Premio_Bruto": 0.76,
      "IR": 0.114,
      "Corretagem": 0.0236,
      "Premio_Liquido": 0.6225,
      "Taxa": 2.8487,
      "Taxa_Dia": 0.1096,
      "Taxa_Mes": 3.29,
      "Volume": 54600,
      "Bid_Volume": 200,
      "Sem_Oferta": false,
      "Liquidez": "ALTA",
      "Score": 6.5,
      "CDI": "SUPERA",
      "Tipo": "CALL",
      "Estrategia": "Call Vendida",
      "Ganho_Por_Lote": 62.25,
      "Ganho_Total": 622.45,
      "Lotes_Carteira": 10,
      "Delta": 0.344,
      "Gamma": 0.1304,
      "Theta": -0.0239,
      "Vega": 0.0258,
      "Rho": 0.0071,
      "Poe": 29.82,
      "Margin": 0,
      "IV": 46.07,
      "Moneyness": "OTM"
    },
    {
      "Acao": "CMIN",
      "Preco_Atual": 4.89,
      "Preco_Medio": 5.66,
      "Quantidade": 3700,
      "Ticker_Opcao": "CMINF520",
      "Estilo": "EUROPEAN",
      "Venc": "2026-06-19",
      "Dias_ate_Venc": 26,
      "Strike": 5.06,
      "Posicao": "OTM",
      "Dist_Strike": "+3.5%",
      "Premio_Bruto": 0.16,
      "IR": 0.024,
      "Corretagem": 0.0051,
      "Premio_Liquido": 0.1309,
      "Taxa": 2.6777,
      "Taxa_Dia": 0.103,
      "Taxa_Mes": 3.09,
      "Volume": 15600,
      "Bid_Volume": 1000,
      "Sem_Oferta": false,
      "Liquidez": "ALTA",
      "Score": 6.5,
      "CDI": "SUPERA",
      "Tipo": "CALL",
      "Estrategia": "Call Vendida",
      "Ganho_Por_Lote": 13.09,
      "Ganho_Total": 484.48,
      "Lotes_Carteira": 37,
      "Delta": 0.501,
      "Gamma": 0.9842,
      "Theta": -0.0044,
      "Vega": 0.0064,
      "Rho": 0.0024,
      "Poe": 46.87,
      "Margin": 0,
      "IV": 26.28,
      "Moneyness": "OTM"
    },
    {
      "Acao": "POSI",
      "Preco_Atual": 4.44,
      "Preco_Medio": 5.06,
      "Quantidade": 200,
      "Ticker_Opcao": "POSIF455",
      "Estilo": "AMERICAN",
      "Venc": "2026-06-19",
      "Dias_ate_Venc": 26,
      "Strike": 4.55,
      "Posicao": "OTM",
      "Dist_Strike": "+2.5%",
      "Premio_Bruto": 0.21,
      "IR": 0.0315,
      "Corretagem": 0.0046,
      "Premio_Liquido": 0.1739,
      "Taxa": 3.9178,
      "Taxa_Dia": 0.1507,
      "Taxa_Mes": 4.52,
      "Volume": 500,
      "Bid_Volume": 2000,
      "Sem_Oferta": false,
      "Liquidez": "ALTA",
      "Score": 6.5,
      "CDI": "SUPERA",
      "Tipo": "CALL",
      "Estrategia": "Call Vendida",
      "Ganho_Por_Lote": 17.39,
      "Ganho_Total": 34.79,
      "Lotes_Carteira": 2,
      "Delta": 0.495,
      "Gamma": 0.7108,
      "Theta": -0.0054,
      "Vega": 0.0057,
      "Rho": 0.0021,
      "Poe": 44.46,
      "Margin": 0,
      "IV": 40.4,
      "Moneyness": "OTM"
    },
    {
      "Acao": "B3SA",
      "Preco_Atual": 17.59,
      "Preco_Medio": 18.43,
      "Quantidade": 500,
      "Ticker_Opcao": "B3SAR172",
      "Estilo": "EUROPEAN",
      "Venc": "2026-06-19",
      "Dias_ate_Venc": 26,
      "Strike": 17.22,
      "Posicao": "OTM",
      "Dist_Strike": "-2.1%",
      "Premio_Bruto": 0.63,
      "IR": 0.0945,
      "Corretagem": 0.0172,
      "Premio_Liquido": 0.5183,
      "Taxa": 2.9464,
      "Taxa_Dia": 0.1133,
      "Taxa_Mes": 3.4,
      "Volume": 59400,
      "Bid_Volume": 400,
      "Sem_Oferta": false,
      "Liquidez": "ALTA",
      "Score": 6.5,
      "CDI": "SUPERA",
      "Tipo": "PUT",
      "Estrategia": "Put Vendida",
      "Garantia_Por_Lote": 1722,
      "Lotes_Possiveis": 43,
      "Garantia_Total": 74046,
      "Ganho_Total": 2228.6,
      "Limite_Put": 75000,
      "Pct_Limite_Usado": 98.7,
      "Delta": -0.414,
      "Gamma": 0.199,
      "Theta": -0.0102,
      "Vega": 0.0216,
      "Rho": -0.008,
      "Poe": 45.81,
      "Margin": 0,
      "IV": 35.43,
      "Moneyness": "ATM"
    },
    {
      "Acao": "CYRE",
      "Preco_Atual": 21.85,
      "Preco_Medio": 26.71,
      "Quantidade": 1000,
      "Ticker_Opcao": "CYREF225",
      "Estilo": "AMERICAN",
      "Venc": "2026-06-19",
      "Dias_ate_Venc": 26,
      "Strike": 22.55,
      "Posicao": "OTM",
      "Dist_Strike": "+3.2%",
      "Premio_Bruto": 1.17,
      "IR": 0.1755,
      "Corretagem": 0.0226,
      "Premio_Liquido": 0.9719,
      "Taxa": 4.4483,
      "Taxa_Dia": 0.1711,
      "Taxa_Mes": 5.13,
      "Volume": 4000,
      "Bid_Volume": 0,
      "Sem_Oferta": true,
      "Liquidez": "ALTA",
      "Score": 5.5,
      "CDI": "SUPERA",
      "Tipo": "CALL",
      "Estrategia": "Call Vendida",
      "Ganho_Por_Lote": 97.19,
      "Ganho_Total": 971.95,
      "Lotes_Carteira": 10,
      "Delta": 0.533,
      "Gamma": 0.1382,
      "Theta": -0.0281,
      "Vega": 0.0284,
      "Rho": 0.011,
      "Poe": 48.15,
      "Margin": 0,
      "IV": 40.15,
      "Moneyness": "OTM"
    },
    {
      "Acao": "CYRE",
      "Preco_Atual": 21.85,
      "Preco_Medio": 26.71,
      "Quantidade": 1000,
      "Ticker_Opcao": "CYREF230",
      "Estilo": "AMERICAN",
      "Venc": "2026-06-19",
      "Dias_ate_Venc": 26,
      "Strike": 23.05,
      "Posicao": "OTM",
      "Dist_Strike": "+5.5%",
      "Premio_Bruto": 0.88,
      "IR": 0.132,
      "Corretagem": 0.0231,
      "Premio_Liquido": 0.7249,
      "Taxa": 3.3178,
      "Taxa_Dia": 0.1276,
      "Taxa_Mes": 3.83,
      "Volume": 3500,
      "Bid_Volume": 0,
      "Sem_Oferta": true,
      "Liquidez": "ALTA",
      "Score": 5.5,
      "CDI": "SUPERA",
      "Tipo": "CALL",
      "Estrategia": "Call Vendida",
      "Ganho_Por_Lote": 72.5,
      "Ganho_Total": 724.95,
      "Lotes_Carteira": 10,
      "Delta": 0.407,
      "Gamma": 0.1375,
      "Theta": -0.0257,
      "Vega": 0.0272,
      "Rho": 0.0084,
      "Poe": 35.81,
      "Margin": 0,
      "IV": 44.31,
      "Moneyness": "OTM"
    },
    {
      "Acao": "CYRE",
      "Preco_Atual": 21.85,
      "Preco_Medio": 26.71,
      "Quantidade": 1000,
      "Ticker_Opcao": "CYREF243",
      "Estilo": "EUROPEAN",
      "Venc": "2026-06-19",
      "Dias_ate_Venc": 26,
      "Strike": 24.3,
      "Posicao": "OTM",
      "Dist_Strike": "+11.2%",
      "Premio_Bruto": 0.5,
      "IR": 0.075,
      "Corretagem": 0.0243,
      "Premio_Liquido": 0.4007,
      "Taxa": 1.8339,
      "Taxa_Dia": 0.0705,
      "Taxa_Mes": 2.12,
      "Volume": 400,
      "Bid_Volume": 500,
      "Sem_Oferta": false,
      "Liquidez": "ALTA",
      "Score": 5.5,
      "CDI": "SUPERA",
      "Tipo": "CALL",
      "Estrategia": "Call Vendida",
      "Ganho_Por_Lote": 40.07,
      "Ganho_Total": 400.7,
      "Lotes_Carteira": 10,
      "Delta": 0.26,
      "Gamma": 0.1149,
      "Theta": -0.0206,
      "Vega": 0.0228,
      "Rho": 0.0054,
      "Poe": 22,
      "Margin": 0,
      "IV": 43.82,
      "Moneyness": "OTM"
    },
    {
      "Acao": "CMIN",
      "Preco_Atual": 4.89,
      "Preco_Medio": 5.66,
      "Quantidade": 3700,
      "Ticker_Opcao": "CMINF530",
      "Estilo": "AMERICAN",
      "Venc": "2026-06-19",
      "Dias_ate_Venc": 26,
      "Strike": 5.16,
      "Posicao": "OTM",
      "Dist_Strike": "+5.5%",
      "Premio_Bruto": 0.11,
      "IR": 0.0165,
      "Corretagem": 0.0052,
      "Premio_Liquido": 0.0883,
      "Taxa": 1.8065,
      "Taxa_Dia": 0.0695,
      "Taxa_Mes": 2.08,
      "Volume": 44200,
      "Bid_Volume": 35000,
      "Sem_Oferta": false,
      "Liquidez": "ALTA",
      "Score": 5.5,
      "CDI": "SUPERA",
      "Tipo": "CALL",
      "Estrategia": "Call Vendida",
      "Ganho_Por_Lote": 8.83,
      "Ganho_Total": 326.86,
      "Lotes_Carteira": 37,
      "Delta": 0.387,
      "Gamma": 0.9485,
      "Theta": -0.004,
      "Vega": 0.0061,
      "Rho": 0.0019,
      "Poe": 35.64,
      "Margin": 0,
      "IV": 26.23,
      "Moneyness": "OTM"
    },
    {
      "Acao": "BBAS",
      "Preco_Atual": 21.54,
      "Preco_Medio": 22.58,
      "Quantidade": 1000,
      "Ticker_Opcao": "BBASF227W2",
      "Estilo": "AMERICAN",
      "Venc": "2026-06-12",
      "Dias_ate_Venc": 21,
      "Strike": 22.76,
      "Posicao": "OTM",
      "Dist_Strike": "+5.7%",
      "Premio_Bruto": 0.36,
      "IR": 0.054,
      "Corretagem": 0.0228,
      "Premio_Liquido": 0.2832,
      "Taxa": 1.3149,
      "Taxa_Dia": 0.0626,
      "Taxa_Mes": 1.88,
      "Volume": 700,
      "Bid_Volume": 1000,
      "Sem_Oferta": false,
      "Liquidez": "ALTA",
      "Score": 5.5,
      "CDI": "SUPERA",
      "Tipo": "CALL",
      "Estrategia": "Call Vendida",
      "Ganho_Por_Lote": 28.32,
      "Ganho_Total": 283.24,
      "Lotes_Carteira": 10,
      "Delta": 0.328,
      "Gamma": 0.1906,
      "Theta": -0.0201,
      "Vega": 0.0225,
      "Rho": 0.0056,
      "Poe": 29.67,
      "Margin": 0,
      "IV": 29.18,
      "Moneyness": "OTM"
    },
    {
      "Acao": "BBAS",
      "Preco_Atual": 21.54,
      "Preco_Medio": 22.58,
      "Quantidade": 1000,
      "Ticker_Opcao": "BBASF224",
      "Estilo": "AMERICAN",
      "Venc": "2026-06-19",
      "Dias_ate_Venc": 26,
      "Strike": 22.1,
      "Posicao": "OTM",
      "Dist_Strike": "+2.6%",
      "Premio_Bruto": 0.64,
      "IR": 0.096,
      "Corretagem": 0.0221,
      "Premio_Liquido": 0.5219,
      "Taxa": 2.4229,
      "Taxa_Dia": 0.0932,
      "Taxa_Mes": 2.8,
      "Volume": 3734400,
      "Bid_Volume": 100,
      "Sem_Oferta": false,
      "Liquidez": "ALTA",
      "Score": 5.5,
      "CDI": "SUPERA",
      "Tipo": "CALL",
      "Estrategia": "Call Vendida",
      "Ganho_Por_Lote": 52.19,
      "Ganho_Total": 521.9,
      "Lotes_Carteira": 10,
      "Delta": 0.451,
      "Gamma": 0.1889,
      "Theta": -0.0211,
      "Vega": 0.0272,
      "Rho": 0.0093,
      "Poe": 41.25,
      "Margin": 0,
      "IV": 29.25,
      "Moneyness": "OTM"
    },
    {
      "Acao": "BBAS",
      "Preco_Atual": 21.54,
      "Preco_Medio": 22.58,
      "Quantidade": 1000,
      "Ticker_Opcao": "BBASF225",
      "Estilo": "EUROPEAN",
      "Venc": "2026-06-19",
      "Dias_ate_Venc": 26,
      "Strike": 22.35,
      "Posicao": "OTM",
      "Dist_Strike": "+3.8%",
      "Premio_Bruto": 0.54,
      "IR": 0.081,
      "Corretagem": 0.0224,
      "Premio_Liquido": 0.4367,
      "Taxa": 2.0272,
      "Taxa_Dia": 0.078,
      "Taxa_Mes": 2.34,
      "Volume": 105700,
      "Bid_Volume": 600,
      "Sem_Oferta": false,
      "Liquidez": "ALTA",
      "Score": 5.5,
      "CDI": "SUPERA",
      "Tipo": "CALL",
      "Estrategia": "Call Vendida",
      "Ganho_Por_Lote": 43.67,
      "Ganho_Total": 436.65,
      "Lotes_Carteira": 10,
      "Delta": 0.402,
      "Gamma": 0.1848,
      "Theta": -0.0202,
      "Vega": 0.0266,
      "Rho": 0.0083,
      "Poe": 36.48,
      "Margin": 0,
      "IV": 29.38,
      "Moneyness": "OTM"
    },
    {
      "Acao": "BBAS",
      "Preco_Atual": 21.54,
      "Preco_Medio": 22.58,
      "Quantidade": 1000,
      "Ticker_Opcao": "BBASF229",
      "Estilo": "AMERICAN",
      "Venc": "2026-06-19",
      "Dias_ate_Venc": 26,
      "Strike": 22.6,
      "Posicao": "OTM",
      "Dist_Strike": "+4.9%",
      "Premio_Bruto": 0.46,
      "IR": 0.069,
      "Corretagem": 0.0226,
      "Premio_Liquido": 0.3684,
      "Taxa": 1.7103,
      "Taxa_Dia": 0.0658,
      "Taxa_Mes": 1.97,
      "Volume": 230300,
      "Bid_Volume": 100,
      "Sem_Oferta": false,
      "Liquidez": "ALTA",
      "Score": 5.5,
      "CDI": "SUPERA",
      "Tipo": "CALL",
      "Estrategia": "Call Vendida",
      "Ganho_Por_Lote": 36.84,
      "Ganho_Total": 368.4,
      "Lotes_Carteira": 10,
      "Delta": 0.386,
      "Gamma": 0.1814,
      "Theta": -0.02,
      "Vega": 0.0265,
      "Rho": 0.008,
      "Poe": 34.9,
      "Margin": 0,
      "IV": 27.42,
      "Moneyness": "OTM"
    },
    {
      "Acao": "BBAS",
      "Preco_Atual": 21.54,
      "Preco_Medio": 22.58,
      "Quantidade": 1000,
      "Ticker_Opcao": "BBASF231",
      "Estilo": "EUROPEAN",
      "Venc": "2026-06-19",
      "Dias_ate_Venc": 26,
      "Strike": 22.85,
      "Posicao": "OTM",
      "Dist_Strike": "+6.1%",
      "Premio_Bruto": 0.38,
      "IR": 0.057,
      "Corretagem": 0.0229,
      "Premio_Liquido": 0.3002,
      "Taxa": 1.3935,
      "Taxa_Dia": 0.0536,
      "Taxa_Mes": 1.61,
      "Volume": 280700,
      "Bid_Volume": 100,
      "Sem_Oferta": false,
      "Liquidez": "ALTA",
      "Score": 5.5,
      "CDI": "SUPERA",
      "Tipo": "CALL",
      "Estrategia": "Call Vendida",
      "Ganho_Por_Lote": 30.02,
      "Ganho_Total": 300.15,
      "Lotes_Carteira": 10,
      "Delta": 0.344,
      "Gamma": 0.1745,
      "Theta": -0.0189,
      "Vega": 0.0255,
      "Rho": 0.0072,
      "Poe": 30.84,
      "Margin": 0,
      "IV": 27.32,
      "Moneyness": "OTM"
    },
    {
      "Acao": "ISAE",
      "Preco_Atual": 30.08,
      "Preco_Medio": 28.72,
      "Quantidade": 700,
      "Ticker_Opcao": "ISAEF314",
      "Estilo": "AMERICAN",
      "Venc": "2026-06-19",
      "Dias_ate_Venc": 26,
      "Strike": 31.12,
      "Posicao": "OTM",
      "Dist_Strike": "+3.5%",
      "Premio_Bruto": 0.51,
      "IR": 0.0765,
      "Corretagem": 0.0311,
      "Premio_Liquido": 0.4024,
      "Taxa": 1.3377,
      "Taxa_Dia": 0.0514,
      "Taxa_Mes": 1.54,
      "Volume": 5200,
      "Bid_Volume": 100,
      "Sem_Oferta": false,
      "Liquidez": "ALTA",
      "Score": 5.5,
      "CDI": "SUPERA",
      "Tipo": "CALL",
      "Estrategia": "Call Vendida",
      "Ganho_Por_Lote": 40.24,
      "Ganho_Total": 281.67,
      "Lotes_Carteira": 7,
      "Delta": 0.353,
      "Gamma": 0.1649,
      "Theta": -0.0218,
      "Vega": 0.0355,
      "Rho": 0.0103,
      "Poe": 32.51,
      "Margin": 0,
      "IV": 23.46,
      "Moneyness": "OTM"
    },
    {
      "Acao": "KLBN",
      "Preco_Atual": 17,
      "Preco_Medio": 20.09,
      "Quantidade": 1000,
      "Ticker_Opcao": "KLBNF173",
      "Estilo": "EUROPEAN",
      "Venc": "2026-06-19",
      "Dias_ate_Venc": 26,
      "Strike": 17.36,
      "Posicao": "OTM",
      "Dist_Strike": "+2.1%",
      "Premio_Bruto": 0.3,
      "IR": 0.045,
      "Corretagem": 0.0174,
      "Premio_Liquido": 0.2376,
      "Taxa": 1.3979,
      "Taxa_Dia": 0.0538,
      "Taxa_Mes": 1.61,
      "Volume": 19000,
      "Bid_Volume": 400,
      "Sem_Oferta": false,
      "Liquidez": "ALTA",
      "Score": 5.5,
      "CDI": "SUPERA",
      "Tipo": "CALL",
      "Estrategia": "Call Vendida",
      "Ganho_Por_Lote": 23.76,
      "Ganho_Total": 237.64,
      "Lotes_Carteira": 10,
      "Delta": 0.413,
      "Gamma": 0.3856,
      "Theta": -0.0114,
      "Vega": 0.0211,
      "Rho": 0.0069,
      "Poe": 38.99,
      "Margin": 0,
      "IV": 19.06,
      "Moneyness": "OTM"
    },
    {
      "Acao": "B3SA",
      "Preco_Atual": 17.59,
      "Preco_Medio": 18.43,
      "Quantidade": 500,
      "Ticker_Opcao": "B3SAF183W2",
      "Estilo": "AMERICAN",
      "Venc": "2026-06-12",
      "Dias_ate_Venc": 21,
      "Strike": 18.31,
      "Posicao": "OTM",
      "Dist_Strike": "+4.1%",
      "Premio_Bruto": 0.56,
      "IR": 0.084,
      "Corretagem": 0.0183,
      "Premio_Liquido": 0.4577,
      "Taxa": 2.602,
      "Taxa_Dia": 0.1239,
      "Taxa_Mes": 3.72,
      "Volume": 200,
      "Bid_Volume": 0,
      "Sem_Oferta": true,
      "Liquidez": "ALTA",
      "Score": 5.5,
      "CDI": "SUPERA",
      "Tipo": "CALL",
      "Estrategia": "Call Vendida",
      "Ganho_Por_Lote": 45.77,
      "Ganho_Total": 228.85,
      "Lotes_Carteira": 5,
      "Delta": 0.411,
      "Gamma": 0.2171,
      "Theta": -0.0204,
      "Vega": 0.0198,
      "Rho": 0.0056,
      "Poe": 37.18,
      "Margin": 0,
      "IV": 38.25,
      "Moneyness": "OTM"
    },
    {
      "Acao": "B3SA",
      "Preco_Atual": 17.59,
      "Preco_Medio": 18.43,
      "Quantidade": 500,
      "Ticker_Opcao": "B3SAF180",
      "Estilo": "EUROPEAN",
      "Venc": "2026-06-19",
      "Dias_ate_Venc": 26,
      "Strike": 17.97,
      "Posicao": "OTM",
      "Dist_Strike": "+2.2%",
      "Premio_Bruto": 0.58,
      "IR": 0.087,
      "Corretagem": 0.018,
      "Premio_Liquido": 0.475,
      "Taxa": 2.7006,
      "Taxa_Dia": 0.1039,
      "Taxa_Mes": 3.12,
      "Volume": 43000,
      "Bid_Volume": 0,
      "Sem_Oferta": true,
      "Liquidez": "ALTA",
      "Score": 5.5,
      "CDI": "SUPERA",
      "Tipo": "CALL",
      "Estrategia": "Call Vendida",
      "Ganho_Por_Lote": 47.5,
      "Ganho_Total": 237.51,
      "Lotes_Carteira": 5,
      "Delta": 0.5,
      "Gamma": 0.2002,
      "Theta": -0.0199,
      "Vega": 0.0225,
      "Rho": 0.0083,
      "Poe": 45.46,
      "Margin": 0,
      "IV": 28.13,
      "Moneyness": "OTM"
    },
    {
      "Acao": "B3SA",
      "Preco_Atual": 17.59,
      "Preco_Medio": 18.43,
      "Quantidade": 500,
      "Ticker_Opcao": "B3SAF182",
      "Estilo": "AMERICAN",
      "Venc": "2026-06-19",
      "Dias_ate_Venc": 26,
      "Strike": 18.22,
      "Posicao": "OTM",
      "Dist_Strike": "+3.6%",
      "Premio_Bruto": 0.48,
      "IR": 0.072,
      "Corretagem": 0.0182,
      "Premio_Liquido": 0.3898,
      "Taxa": 2.2159,
      "Taxa_Dia": 0.0852,
      "Taxa_Mes": 2.56,
      "Volume": 161900,
      "Bid_Volume": 100,
      "Sem_Oferta": false,
      "Liquidez": "ALTA",
      "Score": 5.5,
      "CDI": "SUPERA",
      "Tipo": "CALL",
      "Estrategia": "Call Vendida",
      "Ganho_Por_Lote": 38.98,
      "Ganho_Total": 194.89,
      "Lotes_Carteira": 5,
      "Delta": 0.392,
      "Gamma": 0.1961,
      "Theta": -0.0181,
      "Vega": 0.0213,
      "Rho": 0.0065,
      "Poe": 34.9,
      "Margin": 0,
      "IV": 33.93,
      "Moneyness": "OTM"
    },
    {
      "Acao": "B3SA",
      "Preco_Atual": 17.59,
      "Preco_Medio": 18.43,
      "Quantidade": 500,
      "Ticker_Opcao": "B3SAF185",
      "Estilo": "EUROPEAN",
      "Venc": "2026-06-19",
      "Dias_ate_Venc": 26,
      "Strike": 18.47,
      "Posicao": "OTM",
      "Dist_Strike": "+5.0%",
      "Premio_Bruto": 0.48,
      "IR": 0.072,
      "Corretagem": 0.0185,
      "Premio_Liquido": 0.3895,
      "Taxa": 2.2145,
      "Taxa_Dia": 0.0852,
      "Taxa_Mes": 2.56,
      "Volume": 86200,
      "Bid_Volume": 100,
      "Sem_Oferta": false,
      "Liquidez": "ALTA",
      "Score": 5.5,
      "CDI": "SUPERA",
      "Tipo": "CALL",
      "Estrategia": "Call Vendida",
      "Ganho_Por_Lote": 38.95,
      "Ganho_Total": 194.76,
      "Lotes_Carteira": 5,
      "Delta": 0.404,
      "Gamma": 0.1943,
      "Theta": -0.0186,
      "Vega": 0.0219,
      "Rho": 0.0068,
      "Poe": 36.08,
      "Margin": 0,
      "IV": 32.5,
      "Moneyness": "OTM"
    },
    {
      "Acao": "B3SA",
      "Preco_Atual": 17.59,
      "Preco_Medio": 18.43,
      "Quantidade": 500,
      "Ticker_Opcao": "B3SAF187",
      "Estilo": "AMERICAN",
      "Venc": "2026-06-19",
      "Dias_ate_Venc": 26,
      "Strike": 18.72,
      "Posicao": "OTM",
      "Dist_Strike": "+6.4%",
      "Premio_Bruto": 0.33,
      "IR": 0.0495,
      "Corretagem": 0.0187,
      "Premio_Liquido": 0.2618,
      "Taxa": 1.4882,
      "Taxa_Dia": 0.0572,
      "Taxa_Mes": 1.72,
      "Volume": 116100,
      "Bid_Volume": 100,
      "Sem_Oferta": false,
      "Liquidez": "ALTA",
      "Score": 5.5,
      "CDI": "SUPERA",
      "Tipo": "CALL",
      "Estrategia": "Call Vendida",
      "Ganho_Por_Lote": 26.18,
      "Ganho_Total": 130.89,
      "Lotes_Carteira": 5,
      "Delta": 0.359,
      "Gamma": 0.1875,
      "Theta": -0.0177,
      "Vega": 0.0211,
      "Rho": 0.006,
      "Poe": 31.74,
      "Margin": 0,
      "IV": 29.14,
      "Moneyness": "OTM"
    },
    {
      "Acao": "CYRE",
      "Preco_Atual": 21.85,
      "Preco_Medio": 26.71,
      "Quantidade": 1000,
      "Ticker_Opcao": "CYRER200",
      "Estilo": "EUROPEAN",
      "Venc": "2026-06-19",
      "Dias_ate_Venc": 26,
      "Strike": 20.05,
      "Posicao": "OTM",
      "Dist_Strike": "-8.2%",
      "Premio_Bruto": 0.38,
      "IR": 0.057,
      "Corretagem": 0.0201,
      "Premio_Liquido": 0.3029,
      "Taxa": 1.3865,
      "Taxa_Dia": 0.0533,
      "Taxa_Mes": 1.6,
      "Volume": 8900,
      "Bid_Volume": 200,
      "Sem_Oferta": false,
      "Liquidez": "ALTA",
      "Score": 5.5,
      "CDI": "SUPERA",
      "Tipo": "PUT",
      "Estrategia": "Put Vendida",
      "Garantia_Por_Lote": 2005,
      "Lotes_Possiveis": 37,
      "Garantia_Total": 74185,
      "Ganho_Total": 1120.91,
      "Limite_Put": 75000,
      "Pct_Limite_Usado": 98.9,
      "Delta": -0.199,
      "Gamma": 0.0989,
      "Theta": -0.0125,
      "Vega": 0.0196,
      "Rho": -0.0048,
      "Poe": 23.71,
      "Margin": 0,
      "IV": 42.55,
      "Moneyness": "OTM"
    },
    {
      "Acao": "CYRE",
      "Preco_Atual": 21.85,
      "Preco_Medio": 26.71,
      "Quantidade": 1000,
      "Ticker_Opcao": "CYRER205",
      "Estilo": "EUROPEAN",
      "Venc": "2026-06-19",
      "Dias_ate_Venc": 26,
      "Strike": 20.55,
      "Posicao": "OTM",
      "Dist_Strike": "-5.9%",
      "Premio_Bruto": 0.58,
      "IR": 0.087,
      "Corretagem": 0.0206,
      "Premio_Liquido": 0.4724,
      "Taxa": 2.1622,
      "Taxa_Dia": 0.0832,
      "Taxa_Mes": 2.49,
      "Volume": 1500,
      "Bid_Volume": 200,
      "Sem_Oferta": false,
      "Liquidez": "ALTA",
      "Score": 5.5,
      "CDI": "SUPERA",
      "Tipo": "PUT",
      "Estrategia": "Put Vendida",
      "Garantia_Por_Lote": 2055,
      "Lotes_Possiveis": 36,
      "Garantia_Total": 73980,
      "Ganho_Total": 1700.82,
      "Limite_Put": 75000,
      "Pct_Limite_Usado": 98.6,
      "Delta": -0.258,
      "Gamma": 0.1144,
      "Theta": -0.014,
      "Vega": 0.0226,
      "Rho": -0.0063,
      "Poe": 30.1,
      "Margin": 0,
      "IV": 45.08,
      "Moneyness": "OTM"
    },
    {
      "Acao": "CYRE",
      "Preco_Atual": 21.85,
      "Preco_Medio": 26.71,
      "Quantidade": 1000,
      "Ticker_Opcao": "CYRER210",
      "Estilo": "EUROPEAN",
      "Venc": "2026-06-19",
      "Dias_ate_Venc": 26,
      "Strike": 21.05,
      "Posicao": "OTM",
      "Dist_Strike": "-3.7%",
      "Premio_Bruto": 0.6,
      "IR": 0.09,
      "Corretagem": 0.0211,
      "Premio_Liquido": 0.4889,
      "Taxa": 2.2378,
      "Taxa_Dia": 0.0861,
      "Taxa_Mes": 2.58,
      "Volume": 7400,
      "Bid_Volume": 1000,
      "Sem_Oferta": false,
      "Liquidez": "ALTA",
      "Score": 5.5,
      "CDI": "SUPERA",
      "Tipo": "PUT",
      "Estrategia": "Put Vendida",
      "Garantia_Por_Lote": 2105,
      "Lotes_Possiveis": 35,
      "Garantia_Total": 73675,
      "Ganho_Total": 1711.32,
      "Limite_Put": 75000,
      "Pct_Limite_Usado": 98.2,
      "Delta": -0.271,
      "Gamma": 0.1153,
      "Theta": -0.0146,
      "Vega": 0.0237,
      "Rho": -0.0068,
      "Poe": 31.58,
      "Margin": 0,
      "IV": 43.91,
      "Moneyness": "OTM"
    },
    {
      "Acao": "CMIG",
      "Preco_Atual": 11.8,
      "Preco_Medio": 12.11,
      "Quantidade": 1200,
      "Ticker_Opcao": "CMIGR132",
      "Estilo": "EUROPEAN",
      "Venc": "2026-06-19",
      "Dias_ate_Venc": 26,
      "Strike": 11.49,
      "Posicao": "OTM",
      "Dist_Strike": "-2.6%",
      "Premio_Bruto": 0.25,
      "IR": 0.0375,
      "Corretagem": 0.0115,
      "Premio_Liquido": 0.201,
      "Taxa": 1.7035,
      "Taxa_Dia": 0.0655,
      "Taxa_Mes": 1.97,
      "Volume": 213000,
      "Bid_Volume": 2000,
      "Sem_Oferta": false,
      "Liquidez": "ALTA",
      "Score": 5.5,
      "CDI": "SUPERA",
      "Tipo": "PUT",
      "Estrategia": "Put Vendida",
      "Garantia_Por_Lote": 1149,
      "Lotes_Possiveis": 65,
      "Garantia_Total": 74685,
      "Ganho_Total": 1306.57,
      "Limite_Put": 75000,
      "Pct_Limite_Usado": 99.6,
      "Delta": -0.42,
      "Gamma": 0.4228,
      "Theta": -0.004,
      "Vega": 0.0144,
      "Rho": -0.0053,
      "Poe": 45.13,
      "Margin": 0,
      "IV": 21.86,
      "Moneyness": "ATM"
    },
    {
      "Acao": "POMO",
      "Preco_Atual": 6.17,
      "Preco_Medio": 6.49,
      "Quantidade": 3200,
      "Ticker_Opcao": "POMOR606",
      "Estilo": "EUROPEAN",
      "Venc": "2026-06-19",
      "Dias_ate_Venc": 26,
      "Strike": 5.99,
      "Posicao": "OTM",
      "Dist_Strike": "-2.9%",
      "Premio_Bruto": 0.14,
      "IR": 0.021,
      "Corretagem": 0.006,
      "Premio_Liquido": 0.113,
      "Taxa": 1.8316,
      "Taxa_Dia": 0.0704,
      "Taxa_Mes": 2.11,
      "Volume": 6200,
      "Bid_Volume": 1100,
      "Sem_Oferta": false,
      "Liquidez": "ALTA",
      "Score": 5.5,
      "CDI": "SUPERA",
      "Tipo": "PUT",
      "Estrategia": "Put Vendida",
      "Garantia_Por_Lote": 599,
      "Lotes_Possiveis": 125,
      "Garantia_Total": 74875,
      "Ganho_Total": 1412.63,
      "Limite_Put": 75000,
      "Pct_Limite_Usado": 99.8,
      "Delta": -0.345,
      "Gamma": 0.7791,
      "Theta": -0.0021,
      "Vega": 0.0072,
      "Rho": -0.0023,
      "Poe": 37.36,
      "Margin": 0,
      "IV": 27.87,
      "Moneyness": "OTM"
    },
    {
      "Acao": "VLID",
      "Preco_Atual": 18.15,
      "Preco_Medio": 21.57,
      "Quantidade": 1000,
      "Ticker_Opcao": "VLIDR173",
      "Estilo": "EUROPEAN",
      "Venc": "2026-06-19",
      "Dias_ate_Venc": 26,
      "Strike": 17.2,
      "Posicao": "OTM",
      "Dist_Strike": "-5.2%",
      "Premio_Bruto": 0.6,
      "IR": 0.09,
      "Corretagem": 0.0172,
      "Premio_Liquido": 0.4928,
      "Taxa": 2.7152,
      "Taxa_Dia": 0.1044,
      "Taxa_Mes": 3.13,
      "Volume": 300,
      "Bid_Volume": 0,
      "Sem_Oferta": true,
      "Liquidez": "ALTA",
      "Score": 5.5,
      "CDI": "SUPERA",
      "Tipo": "PUT",
      "Estrategia": "Put Vendida",
      "Garantia_Por_Lote": 1720,
      "Lotes_Possiveis": 43,
      "Garantia_Total": 73960,
      "Ganho_Total": 2119.04,
      "Limite_Put": 75000,
      "Pct_Limite_Usado": 98.6,
      "Delta": -0.255,
      "Gamma": 0.186,
      "Theta": -0.0079,
      "Vega": 0.0185,
      "Rho": -0.005,
      "Poe": 28.69,
      "Margin": 0,
      "IV": 46.19,
      "Moneyness": "OTM"
    },
    {
      "Acao": "VLID",
      "Preco_Atual": 18.15,
      "Preco_Medio": 21.57,
      "Quantidade": 1000,
      "Ticker_Opcao": "VLIDR178",
      "Estilo": "EUROPEAN",
      "Venc": "2026-06-19",
      "Dias_ate_Venc": 26,
      "Strike": 17.7,
      "Posicao": "OTM",
      "Dist_Strike": "-2.5%",
      "Premio_Bruto": 0.82,
      "IR": 0.123,
      "Corretagem": 0.0177,
      "Premio_Liquido": 0.6793,
      "Taxa": 3.7427,
      "Taxa_Dia": 0.1439,
      "Taxa_Mes": 4.32,
      "Volume": 300,
      "Bid_Volume": 0,
      "Sem_Oferta": true,
      "Liquidez": "ALTA",
      "Score": 5.5,
      "CDI": "SUPERA",
      "Tipo": "PUT",
      "Estrategia": "Put Vendida",
      "Garantia_Por_Lote": 1770,
      "Lotes_Possiveis": 42,
      "Garantia_Total": 74340,
      "Ganho_Total": 2853.06,
      "Limite_Put": 75000,
      "Pct_Limite_Usado": 99.1,
      "Delta": -0.321,
      "Gamma": 0.2054,
      "Theta": -0.0085,
      "Vega": 0.0209,
      "Rho": -0.0064,
      "Poe": 35.65,
      "Margin": 0,
      "IV": 50.07,
      "Moneyness": "OTM"
    },
    {
      "Acao": "BBAS",
      "Preco_Atual": 21.54,
      "Preco_Medio": 22.58,
      "Quantidade": 1000,
      "Ticker_Opcao": "BBASR206",
      "Estilo": "EUROPEAN",
      "Venc": "2026-06-19",
      "Dias_ate_Venc": 26,
      "Strike": 20.6,
      "Posicao": "OTM",
      "Dist_Strike": "-4.4%",
      "Premio_Bruto": 0.39,
      "IR": 0.0585,
      "Corretagem": 0.0206,
      "Premio_Liquido": 0.3109,
      "Taxa": 1.4434,
      "Taxa_Dia": 0.0555,
      "Taxa_Mes": 1.67,
      "Volume": 729100,
      "Bid_Volume": 100,
      "Sem_Oferta": false,
      "Liquidez": "ALTA",
      "Score": 5.5,
      "CDI": "SUPERA",
      "Tipo": "PUT",
      "Estrategia": "Put Vendida",
      "Garantia_Por_Lote": 2060,
      "Lotes_Possiveis": 36,
      "Garantia_Total": 74160,
      "Ganho_Total": 1119.24,
      "Limite_Put": 75000,
      "Pct_Limite_Usado": 98.9,
      "Delta": -0.274,
      "Gamma": 0.159,
      "Theta": -0.0099,
      "Vega": 0.0229,
      "Rho": -0.0064,
      "Poe": 30.8,
      "Margin": 0,
      "IV": 31.23,
      "Moneyness": "OTM"
    },
    {
      "Acao": "BBAS",
      "Preco_Atual": 21.54,
      "Preco_Medio": 22.58,
      "Quantidade": 1000,
      "Ticker_Opcao": "BBASR210",
      "Estilo": "EUROPEAN",
      "Venc": "2026-06-19",
      "Dias_ate_Venc": 26,
      "Strike": 20.85,
      "Posicao": "OTM",
      "Dist_Strike": "-3.2%",
      "Premio_Bruto": 0.48,
      "IR": 0.072,
      "Corretagem": 0.0209,
      "Premio_Liquido": 0.3871,
      "Taxa": 1.7974,
      "Taxa_Dia": 0.0691,
      "Taxa_Mes": 2.07,
      "Volume": 831500,
      "Bid_Volume": 300,
      "Sem_Oferta": false,
      "Liquidez": "ALTA",
      "Score": 5.5,
      "CDI": "SUPERA",
      "Tipo": "PUT",
      "Estrategia": "Put Vendida",
      "Garantia_Por_Lote": 2085,
      "Lotes_Possiveis": 35,
      "Garantia_Total": 72975,
      "Ganho_Total": 1355.02,
      "Limite_Put": 75000,
      "Pct_Limite_Usado": 97.3,
      "Delta": -0.334,
      "Gamma": 0.1744,
      "Theta": -0.0103,
      "Vega": 0.0249,
      "Rho": -0.0079,
      "Poe": 37.05,
      "Margin": 0,
      "IV": 30.22,
      "Moneyness": "OTM"
    },
    {
      "Acao": "BBAS",
      "Preco_Atual": 21.54,
      "Preco_Medio": 22.58,
      "Quantidade": 1000,
      "Ticker_Opcao": "BBASR214",
      "Estilo": "EUROPEAN",
      "Venc": "2026-06-19",
      "Dias_ate_Venc": 26,
      "Strike": 21.1,
      "Posicao": "OTM",
      "Dist_Strike": "-2.0%",
      "Premio_Bruto": 0.55,
      "IR": 0.0825,
      "Corretagem": 0.0211,
      "Premio_Liquido": 0.4464,
      "Taxa": 2.0724,
      "Taxa_Dia": 0.0797,
      "Taxa_Mes": 2.39,
      "Volume": 471200,
      "Bid_Volume": 200,
      "Sem_Oferta": false,
      "Liquidez": "ALTA",
      "Score": 5.5,
      "CDI": "SUPERA",
      "Tipo": "PUT",
      "Estrategia": "Put Vendida",
      "Garantia_Por_Lote": 2110,
      "Lotes_Possiveis": 35,
      "Garantia_Total": 73850,
      "Ganho_Total": 1562.4,
      "Limite_Put": 75000,
      "Pct_Limite_Usado": 98.5,
      "Delta": -0.361,
      "Gamma": 0.1787,
      "Theta": -0.0104,
      "Vega": 0.0258,
      "Rho": -0.0086,
      "Poe": 39.88,
      "Margin": 0,
      "IV": 30.62,
      "Moneyness": "OTM"
    },
    {
      "Acao": "ITUB",
      "Preco_Atual": 40.33,
      "Preco_Medio": 44.54,
      "Quantidade": 500,
      "Ticker_Opcao": "ITUBR431",
      "Estilo": "EUROPEAN",
      "Venc": "2026-06-19",
      "Dias_ate_Venc": 26,
      "Strike": 39.36,
      "Posicao": "OTM",
      "Dist_Strike": "-2.4%",
      "Premio_Bruto": 0.76,
      "IR": 0.114,
      "Corretagem": 0.0394,
      "Premio_Liquido": 0.6066,
      "Taxa": 1.5042,
      "Taxa_Dia": 0.0579,
      "Taxa_Mes": 1.74,
      "Volume": 646300,
      "Bid_Volume": 200,
      "Sem_Oferta": false,
      "Liquidez": "ALTA",
      "Score": 5.5,
      "CDI": "SUPERA",
      "Tipo": "PUT",
      "Estrategia": "Put Vendida",
      "Garantia_Por_Lote": 3936,
      "Lotes_Possiveis": 19,
      "Garantia_Total": 74784,
      "Ganho_Total": 1152.62,
      "Limite_Put": 75000,
      "Pct_Limite_Usado": 99.7,
      "Delta": -0.363,
      "Gamma": 0.1135,
      "Theta": -0.0151,
      "Vega": 0.0479,
      "Rho": -0.0158,
      "Poe": 39.43,
      "Margin": 0,
      "IV": 23.81,
      "Moneyness": "OTM"
    },
    {
      "Acao": "ISAE",
      "Preco_Atual": 30.08,
      "Preco_Medio": 28.72,
      "Quantidade": 700,
      "Ticker_Opcao": "ISAER295",
      "Estilo": "EUROPEAN",
      "Venc": "2026-06-19",
      "Dias_ate_Venc": 26,
      "Strike": 29.12,
      "Posicao": "OTM",
      "Dist_Strike": "-3.2%",
      "Premio_Bruto": 0.51,
      "IR": 0.0765,
      "Corretagem": 0.0291,
      "Premio_Liquido": 0.4044,
      "Taxa": 1.3443,
      "Taxa_Dia": 0.0517,
      "Taxa_Mes": 1.55,
      "Volume": 600,
      "Bid_Volume": 1000,
      "Sem_Oferta": false,
      "Liquidez": "ALTA",
      "Score": 5.5,
      "CDI": "SUPERA",
      "Tipo": "PUT",
      "Estrategia": "Put Vendida",
      "Garantia_Por_Lote": 2912,
      "Lotes_Possiveis": 25,
      "Garantia_Total": 72800,
      "Ganho_Total": 1010.95,
      "Limite_Put": 75000,
      "Pct_Limite_Usado": 97.1,
      "Delta": -0.315,
      "Gamma": 0.158,
      "Theta": -0.0098,
      "Vega": 0.0339,
      "Rho": -0.0101,
      "Poe": 34.28,
      "Margin": 0,
      "IV": 24.55,
      "Moneyness": "OTM"
    },
    {
      "Acao": "ISAE",
      "Preco_Atual": 30.08,
      "Preco_Medio": 28.72,
      "Quantidade": 700,
      "Ticker_Opcao": "ISAER306",
      "Estilo": "EUROPEAN",
      "Venc": "2026-06-19",
      "Dias_ate_Venc": 26,
      "Strike": 29.37,
      "Posicao": "OTM",
      "Dist_Strike": "-2.4%",
      "Premio_Bruto": 0.65,
      "IR": 0.0975,
      "Corretagem": 0.0294,
      "Premio_Liquido": 0.5231,
      "Taxa": 1.7391,
      "Taxa_Dia": 0.0669,
      "Taxa_Mes": 2.01,
      "Volume": 100,
      "Bid_Volume": 200,
      "Sem_Oferta": false,
      "Liquidez": "ALTA",
      "Score": 5.5,
      "CDI": "SUPERA",
      "Tipo": "PUT",
      "Estrategia": "Put Vendida",
      "Garantia_Por_Lote": 2937,
      "Lotes_Possiveis": 25,
      "Garantia_Total": 73425,
      "Ganho_Total": 1307.82,
      "Limite_Put": 75000,
      "Pct_Limite_Usado": 97.9,
      "Delta": -0.292,
      "Gamma": 0.1505,
      "Theta": -0.0098,
      "Vega": 0.0332,
      "Rho": -0.0095,
      "Poe": 31.81,
      "Margin": 0,
      "IV": 29.92,
      "Moneyness": "OTM"
    },
    {
      "Acao": "B3SA",
      "Preco_Atual": 17.59,
      "Preco_Medio": 18.43,
      "Quantidade": 500,
      "Ticker_Opcao": "B3SAR162",
      "Estilo": "EUROPEAN",
      "Venc": "2026-06-19",
      "Dias_ate_Venc": 26,
      "Strike": 16.22,
      "Posicao": "OTM",
      "Dist_Strike": "-7.8%",
      "Premio_Bruto": 0.3,
      "IR": 0.045,
      "Corretagem": 0.0162,
      "Premio_Liquido": 0.2388,
      "Taxa": 1.3575,
      "Taxa_Dia": 0.0522,
      "Taxa_Mes": 1.57,
      "Volume": 62400,
      "Bid_Volume": 100,
      "Sem_Oferta": false,
      "Liquidez": "ALTA",
      "Score": 5.5,
      "CDI": "SUPERA",
      "Tipo": "PUT",
      "Estrategia": "Put Vendida",
      "Garantia_Por_Lote": 1622,
      "Lotes_Possiveis": 46,
      "Garantia_Total": 74612,
      "Ganho_Total": 1098.39,
      "Limite_Put": 75000,
      "Pct_Limite_Usado": 99.5,
      "Delta": -0.183,
      "Gamma": 0.1331,
      "Theta": -0.0082,
      "Vega": 0.015,
      "Rho": -0.0035,
      "Poe": 21.47,
      "Margin": 0,
      "IV": 40.99,
      "Moneyness": "OTM"
    },
    {
      "Acao": "B3SA",
      "Preco_Atual": 17.59,
      "Preco_Medio": 18.43,
      "Quantidade": 500,
      "Ticker_Opcao": "B3SAR165",
      "Estilo": "EUROPEAN",
      "Venc": "2026-06-19",
      "Dias_ate_Venc": 26,
      "Strike": 16.47,
      "Posicao": "OTM",
      "Dist_Strike": "-6.4%",
      "Premio_Bruto": 0.36,
      "IR": 0.054,
      "Corretagem": 0.0165,
      "Premio_Liquido": 0.2895,
      "Taxa": 1.646,
      "Taxa_Dia": 0.0633,
      "Taxa_Mes": 1.9,
      "Volume": 55400,
      "Bid_Volume": 200,
      "Sem_Oferta": false,
      "Liquidez": "ALTA",
      "Score": 5.5,
      "CDI": "SUPERA",
      "Tipo": "PUT",
      "Estrategia": "Put Vendida",
      "Garantia_Por_Lote": 1647,
      "Lotes_Possiveis": 45,
      "Garantia_Total": 74115,
      "Ganho_Total": 1302.88,
      "Limite_Put": 75000,
      "Pct_Limite_Usado": 98.8,
      "Delta": -0.265,
      "Gamma": 0.1671,
      "Theta": -0.0095,
      "Vega": 0.0182,
      "Rho": -0.0051,
      "Poe": 30.38,
      "Margin": 0,
      "IV": 36.59,
      "Moneyness": "OTM"
    },
    {
      "Acao": "B3SA",
      "Preco_Atual": 17.59,
      "Preco_Medio": 18.43,
      "Quantidade": 500,
      "Ticker_Opcao": "B3SAR167",
      "Estilo": "EUROPEAN",
      "Venc": "2026-06-19",
      "Dias_ate_Venc": 26,
      "Strike": 16.72,
      "Posicao": "OTM",
      "Dist_Strike": "-4.9%",
      "Premio_Bruto": 0.44,
      "IR": 0.066,
      "Corretagem": 0.0167,
      "Premio_Liquido": 0.3573,
      "Taxa": 2.0312,
      "Taxa_Dia": 0.0781,
      "Taxa_Mes": 2.34,
      "Volume": 328900,
      "Bid_Volume": 400,
      "Sem_Oferta": false,
      "Liquidez": "ALTA",
      "Score": 5.5,
      "CDI": "SUPERA",
      "Tipo": "PUT",
      "Estrategia": "Put Vendida",
      "Garantia_Por_Lote": 1672,
      "Lotes_Possiveis": 44,
      "Garantia_Total": 73568,
      "Ganho_Total": 1572.03,
      "Limite_Put": 75000,
      "Pct_Limite_Usado": 98.1,
      "Delta": -0.263,
      "Gamma": 0.1636,
      "Theta": -0.0097,
      "Vega": 0.0184,
      "Rho": -0.0051,
      "Poe": 30.08,
      "Margin": 0,
      "IV": 40.77,
      "Moneyness": "OTM"
    },
    {
      "Acao": "B3SA",
      "Preco_Atual": 17.59,
      "Preco_Medio": 18.43,
      "Quantidade": 500,
      "Ticker_Opcao": "B3SAR170",
      "Estilo": "EUROPEAN",
      "Venc": "2026-06-19",
      "Dias_ate_Venc": 26,
      "Strike": 16.97,
      "Posicao": "OTM",
      "Dist_Strike": "-3.5%",
      "Premio_Bruto": 0.53,
      "IR": 0.0795,
      "Corretagem": 0.017,
      "Premio_Liquido": 0.4335,
      "Taxa": 2.4646,
      "Taxa_Dia": 0.0948,
      "Taxa_Mes": 2.84,
      "Volume": 296700,
      "Bid_Volume": 700,
      "Sem_Oferta": false,
      "Liquidez": "ALTA",
      "Score": 5.5,
      "CDI": "SUPERA",
      "Tipo": "PUT",
      "Estrategia": "Put Vendida",
      "Garantia_Por_Lote": 1697,
      "Lotes_Possiveis": 44,
      "Garantia_Total": 74668,
      "Ganho_Total": 1907.53,
      "Limite_Put": 75000,
      "Pct_Limite_Usado": 99.6,
      "Delta": -0.307,
      "Gamma": 0.1762,
      "Theta": -0.0101,
      "Vega": 0.0198,
      "Rho": -0.006,
      "Poe": 34.78,
      "Margin": 0,
      "IV": 40.93,
      "Moneyness": "OTM"
    },
    {
      "Acao": "CYRE",
      "Preco_Atual": 21.85,
      "Preco_Medio": 26.71,
      "Quantidade": 1000,
      "Ticker_Opcao": "CYREF240",
      "Estilo": "AMERICAN",
      "Venc": "2026-06-19",
      "Dias_ate_Venc": 26,
      "Strike": 24.05,
      "Posicao": "OTM",
      "Dist_Strike": "+10.1%",
      "Premio_Bruto": 0.6,
      "IR": 0.09,
      "Corretagem": 0.0241,
      "Premio_Liquido": 0.4859,
      "Taxa": 2.224,
      "Taxa_Dia": 0.0855,
      "Taxa_Mes": 2.57,
      "Volume": 8300,
      "Bid_Volume": 0,
      "Sem_Oferta": true,
      "Liquidez": "ALTA",
      "Score": 4.5,
      "CDI": "SUPERA",
      "Tipo": "CALL",
      "Estrategia": "Call Vendida",
      "Ganho_Por_Lote": 48.59,
      "Ganho_Total": 485.95,
      "Lotes_Carteira": 10,
      "Delta": 0.339,
      "Gamma": 0.1272,
      "Theta": -0.0242,
      "Vega": 0.0262,
      "Rho": 0.0072,
      "Poe": 29.3,
      "Margin": 0,
      "IV": 40.04,
      "Moneyness": "OTM"
    },
    {
      "Acao": "BBSE",
      "Preco_Atual": 34.3,
      "Preco_Medio": 35.69,
      "Quantidade": 600,
      "Ticker_Opcao": "BBSEF376",
      "Estilo": "AMERICAN",
      "Venc": "2026-06-19",
      "Dias_ate_Venc": 26,
      "Strike": 35.04,
      "Posicao": "OTM",
      "Dist_Strike": "+2.2%",
      "Premio_Bruto": 0.49,
      "IR": 0.0735,
      "Corretagem": 0.035,
      "Premio_Liquido": 0.3815,
      "Taxa": 1.1121,
      "Taxa_Dia": 0.0428,
      "Taxa_Mes": 1.28,
      "Volume": 13500,
      "Bid_Volume": 400,
      "Sem_Oferta": false,
      "Liquidez": "ALTA",
      "Score": 4.5,
      "CDI": "SUPERA",
      "Tipo": "CALL",
      "Estrategia": "Call Vendida",
      "Ganho_Por_Lote": 38.15,
      "Ganho_Total": 228.88,
      "Lotes_Carteira": 6,
      "Delta": 0.455,
      "Gamma": 0.2448,
      "Theta": -0.0209,
      "Vega": 0.0437,
      "Rho": 0.0155,
      "Poe": 43.6,
      "Margin": 0,
      "IV": 13.49,
      "Moneyness": "OTM"
    },
    {
      "Acao": "POMO",
      "Preco_Atual": 6.17,
      "Preco_Medio": 6.49,
      "Quantidade": 3200,
      "Ticker_Opcao": "POMOF646",
      "Estilo": "EUROPEAN",
      "Venc": "2026-06-19",
      "Dias_ate_Venc": 26,
      "Strike": 6.39,
      "Posicao": "OTM",
      "Dist_Strike": "+3.6%",
      "Premio_Bruto": 0.11,
      "IR": 0.0165,
      "Corretagem": 0.0064,
      "Premio_Liquido": 0.0871,
      "Taxa": 1.4118,
      "Taxa_Dia": 0.0543,
      "Taxa_Mes": 1.63,
      "Volume": 3500,
      "Bid_Volume": 0,
      "Sem_Oferta": true,
      "Liquidez": "ALTA",
      "Score": 4.5,
      "CDI": "SUPERA",
      "Tipo": "CALL",
      "Estrategia": "Call Vendida",
      "Ganho_Por_Lote": 8.71,
      "Ganho_Total": 278.75,
      "Lotes_Carteira": 32,
      "Delta": 0.413,
      "Gamma": 0.8104,
      "Theta": -0.005,
      "Vega": 0.0077,
      "Rho": 0.0025,
      "Poe": 38.28,
      "Margin": 0,
      "IV": 20.7,
      "Moneyness": "OTM"
    },
    {
      "Acao": "POMO",
      "Preco_Atual": 6.17,
      "Preco_Medio": 6.49,
      "Quantidade": 3200,
      "Ticker_Opcao": "POMOF656",
      "Estilo": "AMERICAN",
      "Venc": "2026-06-19",
      "Dias_ate_Venc": 26,
      "Strike": 6.49,
      "Posicao": "OTM",
      "Dist_Strike": "+5.2%",
      "Premio_Bruto": 0.1,
      "IR": 0.015,
      "Corretagem": 0.0065,
      "Premio_Liquido": 0.0785,
      "Taxa": 1.2724,
      "Taxa_Dia": 0.0489,
      "Taxa_Mes": 1.47,
      "Volume": 5900,
      "Bid_Volume": 1500,
      "Sem_Oferta": false,
      "Liquidez": "ALTA",
      "Score": 4.5,
      "CDI": "SUPERA",
      "Tipo": "CALL",
      "Estrategia": "Call Vendida",
      "Ganho_Por_Lote": 7.85,
      "Ganho_Total": 251.23,
      "Lotes_Carteira": 32,
      "Delta": 0.337,
      "Gamma": 0.7604,
      "Theta": -0.0045,
      "Vega": 0.0072,
      "Rho": 0.002,
      "Poe": 30.94,
      "Margin": 0,
      "IV": 23.81,
      "Moneyness": "OTM"
    },
    {
      "Acao": "VLID",
      "Preco_Atual": 18.15,
      "Preco_Medio": 21.57,
      "Quantidade": 1000,
      "Ticker_Opcao": "VLIDF193",
      "Estilo": "AMERICAN",
      "Venc": "2026-06-19",
      "Dias_ate_Venc": 26,
      "Strike": 19.2,
      "Posicao": "OTM",
      "Dist_Strike": "+5.8%",
      "Premio_Bruto": 0.43,
      "IR": 0.0645,
      "Corretagem": 0.0192,
      "Premio_Liquido": 0.3463,
      "Taxa": 1.908,
      "Taxa_Dia": 0.0734,
      "Taxa_Mes": 2.2,
      "Volume": 12800,
      "Bid_Volume": 0,
      "Sem_Oferta": true,
      "Liquidez": "ALTA",
      "Score": 4.5,
      "CDI": "SUPERA",
      "Tipo": "CALL",
      "Estrategia": "Call Vendida",
      "Ganho_Por_Lote": 34.63,
      "Ganho_Total": 346.3,
      "Lotes_Carteira": 10,
      "Delta": 0.313,
      "Gamma": 0.2053,
      "Theta": -0.0148,
      "Vega": 0.0205,
      "Rho": 0.0055,
      "Poe": 28.01,
      "Margin": 0,
      "IV": 34.62,
      "Moneyness": "OTM"
    },
    {
      "Acao": "ITUB",
      "Preco_Atual": 40.33,
      "Preco_Medio": 44.54,
      "Quantidade": 500,
      "Ticker_Opcao": "ITUBF418W1",
      "Estilo": "AMERICAN",
      "Venc": "2026-06-05",
      "Dias_ate_Venc": 16,
      "Strike": 41.86,
      "Posicao": "OTM",
      "Dist_Strike": "+3.8%",
      "Premio_Bruto": 0.59,
      "IR": 0.0885,
      "Corretagem": 0.0419,
      "Premio_Liquido": 0.4596,
      "Taxa": 1.1397,
      "Taxa_Dia": 0.0712,
      "Taxa_Mes": 2.14,
      "Volume": 1100,
      "Bid_Volume": 0,
      "Sem_Oferta": true,
      "Liquidez": "ALTA",
      "Score": 4.5,
      "CDI": "SUPERA",
      "Tipo": "CALL",
      "Estrategia": "Call Vendida",
      "Ganho_Por_Lote": 45.96,
      "Ganho_Total": 229.82,
      "Lotes_Carteira": 5,
      "Delta": 0.345,
      "Gamma": 0.1402,
      "Theta": -0.0379,
      "Vega": 0.0374,
      "Rho": 0.0085,
      "Poe": 32.15,
      "Margin": 0,
      "IV": 25.97,
      "Moneyness": "OTM"
    },
    {
      "Acao": "ITUB",
      "Preco_Atual": 40.33,
      "Preco_Medio": 44.54,
      "Quantidade": 500,
      "Ticker_Opcao": "ITUBF415",
      "Estilo": "EUROPEAN",
      "Venc": "2026-06-19",
      "Dias_ate_Venc": 26,
      "Strike": 41.19,
      "Posicao": "OTM",
      "Dist_Strike": "+2.1%",
      "Premio_Bruto": 0.85,
      "IR": 0.1275,
      "Corretagem": 0.0412,
      "Premio_Liquido": 0.6813,
      "Taxa": 1.6893,
      "Taxa_Dia": 0.065,
      "Taxa_Mes": 1.95,
      "Volume": 90300,
      "Bid_Volume": 0,
      "Sem_Oferta": true,
      "Liquidez": "ALTA",
      "Score": 4.5,
      "CDI": "SUPERA",
      "Tipo": "CALL",
      "Estrategia": "Call Vendida",
      "Ganho_Por_Lote": 68.13,
      "Ganho_Total": 340.65,
      "Lotes_Carteira": 5,
      "Delta": 0.427,
      "Gamma": 0.1185,
      "Theta": -0.0341,
      "Vega": 0.0502,
      "Rho": 0.0165,
      "Poe": 39.48,
      "Margin": 0,
      "IV": 23.07,
      "Moneyness": "OTM"
    },
    {
      "Acao": "ITUB",
      "Preco_Atual": 40.33,
      "Preco_Medio": 44.54,
      "Quantidade": 500,
      "Ticker_Opcao": "ITUBF417",
      "Estilo": "AMERICAN",
      "Venc": "2026-06-19",
      "Dias_ate_Venc": 26,
      "Strike": 41.44,
      "Posicao": "OTM",
      "Dist_Strike": "+2.8%",
      "Premio_Bruto": 0.75,
      "IR": 0.1125,
      "Corretagem": 0.0414,
      "Premio_Liquido": 0.5961,
      "Taxa": 1.478,
      "Taxa_Dia": 0.0568,
      "Taxa_Mes": 1.71,
      "Volume": 84000,
      "Bid_Volume": 0,
      "Sem_Oferta": true,
      "Liquidez": "ALTA",
      "Score": 4.5,
      "CDI": "SUPERA",
      "Tipo": "CALL",
      "Estrategia": "Call Vendida",
      "Ganho_Por_Lote": 59.61,
      "Ganho_Total": 298.03,
      "Lotes_Carteira": 5,
      "Delta": 0.458,
      "Gamma": 0.1184,
      "Theta": -0.0355,
      "Vega": 0.0514,
      "Rho": 0.0179,
      "Poe": 42.48,
      "Margin": 0,
      "IV": 18.84,
      "Moneyness": "OTM"
    },
    {
      "Acao": "ITUB",
      "Preco_Atual": 40.33,
      "Preco_Medio": 44.54,
      "Quantidade": 500,
      "Ticker_Opcao": "ITUBF420",
      "Estilo": "EUROPEAN",
      "Venc": "2026-06-19",
      "Dias_ate_Venc": 26,
      "Strike": 41.69,
      "Posicao": "OTM",
      "Dist_Strike": "+3.4%",
      "Premio_Bruto": 0.68,
      "IR": 0.102,
      "Corretagem": 0.0417,
      "Premio_Liquido": 0.5363,
      "Taxa": 1.3298,
      "Taxa_Dia": 0.0511,
      "Taxa_Mes": 1.53,
      "Volume": 55300,
      "Bid_Volume": 0,
      "Sem_Oferta": true,
      "Liquidez": "ALTA",
      "Score": 4.5,
      "CDI": "SUPERA",
      "Tipo": "CALL",
      "Estrategia": "Call Vendida",
      "Ganho_Por_Lote": 53.63,
      "Ganho_Total": 268.16,
      "Lotes_Carteira": 5,
      "Delta": 0.372,
      "Gamma": 0.1143,
      "Theta": -0.0321,
      "Vega": 0.0484,
      "Rho": 0.0145,
      "Poe": 34.12,
      "Margin": 0,
      "IV": 23.11,
      "Moneyness": "OTM"
    },
    {
      "Acao": "ITUB",
      "Preco_Atual": 40.33,
      "Preco_Medio": 44.54,
      "Quantidade": 500,
      "Ticker_Opcao": "ITUBF425",
      "Estilo": "EUROPEAN",
      "Venc": "2026-06-19",
      "Dias_ate_Venc": 26,
      "Strike": 42.19,
      "Posicao": "OTM",
      "Dist_Strike": "+4.6%",
      "Premio_Bruto": 0.53,
      "IR": 0.0795,
      "Corretagem": 0.0422,
      "Premio_Liquido": 0.4083,
      "Taxa": 1.0124,
      "Taxa_Dia": 0.0389,
      "Taxa_Mes": 1.17,
      "Volume": 83100,
      "Bid_Volume": 2000,
      "Sem_Oferta": false,
      "Liquidez": "ALTA",
      "Score": 4.5,
      "CDI": "SUPERA",
      "Tipo": "CALL",
      "Estrategia": "Call Vendida",
      "Ganho_Por_Lote": 40.83,
      "Ganho_Total": 204.16,
      "Lotes_Carteira": 5,
      "Delta": 0.32,
      "Gamma": 0.1081,
      "Theta": -0.0297,
      "Vega": 0.0458,
      "Rho": 0.0125,
      "Poe": 29.13,
      "Margin": 0,
      "IV": 22.98,
      "Moneyness": "OTM"
    },
    {
      "Acao": "CXSE",
      "Preco_Atual": 17.41,
      "Preco_Medio": 17.94,
      "Quantidade": 1100,
      "Ticker_Opcao": "CXSEF195",
      "Estilo": "AMERICAN",
      "Venc": "2026-06-19",
      "Dias_ate_Venc": 26,
      "Strike": 17.87,
      "Posicao": "OTM",
      "Dist_Strike": "+2.6%",
      "Premio_Bruto": 0.27,
      "IR": 0.0405,
      "Corretagem": 0.0179,
      "Premio_Liquido": 0.2116,
      "Taxa": 1.2156,
      "Taxa_Dia": 0.0468,
      "Taxa_Mes": 1.4,
      "Volume": 15100,
      "Bid_Volume": 100,
      "Sem_Oferta": false,
      "Liquidez": "ALTA",
      "Score": 4.5,
      "CDI": "SUPERA",
      "Tipo": "CALL",
      "Estrategia": "Call Vendida",
      "Ganho_Por_Lote": 21.16,
      "Ganho_Total": 232.79,
      "Lotes_Carteira": 11,
      "Delta": 0.435,
      "Gamma": 0.3868,
      "Theta": -0.0119,
      "Vega": 0.022,
      "Rho": 0.0075,
      "Poe": 41.25,
      "Margin": 0,
      "IV": 16.04,
      "Moneyness": "OTM"
    },
    {
      "Acao": "POSI",
      "Preco_Atual": 4.44,
      "Preco_Medio": 5.06,
      "Quantidade": 200,
      "Ticker_Opcao": "POSIF490",
      "Estilo": "EUROPEAN",
      "Venc": "2026-06-19",
      "Dias_ate_Venc": 26,
      "Strike": 4.9,
      "Posicao": "OTM",
      "Dist_Strike": "+10.4%",
      "Premio_Bruto": 0.09,
      "IR": 0.0135,
      "Corretagem": 0.0049,
      "Premio_Liquido": 0.0716,
      "Taxa": 1.6126,
      "Taxa_Dia": 0.062,
      "Taxa_Mes": 1.86,
      "Volume": 300,
      "Bid_Volume": 0,
      "Sem_Oferta": true,
      "Liquidez": "ALTA",
      "Score": 4.5,
      "CDI": "SUPERA",
      "Tipo": "CALL",
      "Estrategia": "Call Vendida",
      "Ganho_Por_Lote": 7.16,
      "Ganho_Total": 14.32,
      "Lotes_Carteira": 2,
      "Delta": 0.275,
      "Gamma": 0.594,
      "Theta": -0.0042,
      "Vega": 0.0048,
      "Rho": 0.0012,
      "Poe": 23.41,
      "Margin": 0,
      "IV": 39.57,
      "Moneyness": "OTM"
    },
    {
      "Acao": "POSI",
      "Preco_Atual": 4.44,
      "Preco_Medio": 5.06,
      "Quantidade": 200,
      "Ticker_Opcao": "POSIF495",
      "Estilo": "AMERICAN",
      "Venc": "2026-06-19",
      "Dias_ate_Venc": 26,
      "Strike": 4.95,
      "Posicao": "OTM",
      "Dist_Strike": "+11.5%",
      "Premio_Bruto": 0.08,
      "IR": 0.012,
      "Corretagem": 0.005,
      "Premio_Liquido": 0.0631,
      "Taxa": 1.42,
      "Taxa_Dia": 0.0546,
      "Taxa_Mes": 1.64,
      "Volume": 200,
      "Bid_Volume": 0,
      "Sem_Oferta": true,
      "Liquidez": "ALTA",
      "Score": 4.5,
      "CDI": "SUPERA",
      "Tipo": "CALL",
      "Estrategia": "Call Vendida",
      "Ganho_Por_Lote": 6.31,
      "Ganho_Total": 12.61,
      "Lotes_Carteira": 2,
      "Delta": 0.237,
      "Gamma": 0.5529,
      "Theta": -0.0039,
      "Vega": 0.0044,
      "Rho": 0.001,
      "Poe": 20,
      "Margin": 0,
      "IV": 40.89,
      "Moneyness": "OTM"
    },
    {
      "Acao": "CYRE",
      "Preco_Atual": 21.85,
      "Preco_Medio": 26.71,
      "Quantidade": 1000,
      "Ticker_Opcao": "CYRER195",
      "Estilo": "EUROPEAN",
      "Venc": "2026-06-19",
      "Dias_ate_Venc": 26,
      "Strike": 19.55,
      "Posicao": "OTM",
      "Dist_Strike": "-10.5%",
      "Premio_Bruto": 0.36,
      "IR": 0.054,
      "Corretagem": 0.0196,
      "Premio_Liquido": 0.2864,
      "Taxa": 1.311,
      "Taxa_Dia": 0.0504,
      "Taxa_Mes": 1.51,
      "Volume": 200,
      "Bid_Volume": 0,
      "Sem_Oferta": true,
      "Liquidez": "ALTA",
      "Score": 4.5,
      "CDI": "SUPERA",
      "Tipo": "PUT",
      "Estrategia": "Put Vendida",
      "Garantia_Por_Lote": 1955,
      "Lotes_Possiveis": 38,
      "Garantia_Total": 74290,
      "Ganho_Total": 1088.51,
      "Limite_Put": 75000,
      "Pct_Limite_Usado": 99.1,
      "Delta": -0.149,
      "Gamma": 0.0822,
      "Theta": -0.0106,
      "Vega": 0.0163,
      "Rho": -0.0036,
      "Poe": 18.11,
      "Margin": 0,
      "IV": 47.58,
      "Moneyness": "OTM"
    },
    {
      "Acao": "CYRE",
      "Preco_Atual": 21.85,
      "Preco_Medio": 26.71,
      "Quantidade": 1000,
      "Ticker_Opcao": "CYRER203",
      "Estilo": "EUROPEAN",
      "Venc": "2026-06-19",
      "Dias_ate_Venc": 26,
      "Strike": 20.3,
      "Posicao": "OTM",
      "Dist_Strike": "-7.1%",
      "Premio_Bruto": 0.44,
      "IR": 0.066,
      "Corretagem": 0.0203,
      "Premio_Liquido": 0.3537,
      "Taxa": 1.6188,
      "Taxa_Dia": 0.0623,
      "Taxa_Mes": 1.87,
      "Volume": 2100,
      "Bid_Volume": 0,
      "Sem_Oferta": true,
      "Liquidez": "ALTA",
      "Score": 4.5,
      "CDI": "SUPERA",
      "Tipo": "PUT",
      "Estrategia": "Put Vendida",
      "Garantia_Por_Lote": 2030,
      "Lotes_Possiveis": 36,
      "Garantia_Total": 73080,
      "Ganho_Total": 1273.32,
      "Limite_Put": 75000,
      "Pct_Limite_Usado": 97.4,
      "Delta": -0.209,
      "Gamma": 0.1011,
      "Theta": -0.0129,
      "Vega": 0.0203,
      "Rho": -0.0051,
      "Poe": 24.83,
      "Margin": 0,
      "IV": 44.13,
      "Moneyness": "OTM"
    },
    {
      "Acao": "CMIN",
      "Preco_Atual": 4.89,
      "Preco_Medio": 5.66,
      "Quantidade": 3700,
      "Ticker_Opcao": "CMINR490",
      "Estilo": "EUROPEAN",
      "Venc": "2026-06-19",
      "Dias_ate_Venc": 26,
      "Strike": 4.76,
      "Posicao": "OTM",
      "Dist_Strike": "-2.7%",
      "Premio_Bruto": 0.07,
      "IR": 0.0105,
      "Corretagem": 0.0048,
      "Premio_Liquido": 0.0547,
      "Taxa": 1.1194,
      "Taxa_Dia": 0.0431,
      "Taxa_Mes": 1.29,
      "Volume": 130900,
      "Bid_Volume": 2000,
      "Sem_Oferta": false,
      "Liquidez": "ALTA",
      "Score": 4.5,
      "CDI": "SUPERA",
      "Tipo": "PUT",
      "Estrategia": "Put Vendida",
      "Garantia_Por_Lote": 476,
      "Lotes_Possiveis": 157,
      "Garantia_Total": 74732,
      "Ganho_Total": 859.42,
      "Limite_Put": 75000,
      "Pct_Limite_Usado": 99.6,
      "Delta": -0.29,
      "Gamma": 0.8583,
      "Theta": -0.0018,
      "Vega": 0.0054,
      "Rho": -0.0015,
      "Poe": 31.85,
      "Margin": 0,
      "IV": 24.32,
      "Moneyness": "OTM"
    },
    {
      "Acao": "POMO",
      "Preco_Atual": 6.17,
      "Preco_Medio": 6.49,
      "Quantidade": 3200,
      "Ticker_Opcao": "POMOR596",
      "Estilo": "EUROPEAN",
      "Venc": "2026-06-19",
      "Dias_ate_Venc": 26,
      "Strike": 5.89,
      "Posicao": "OTM",
      "Dist_Strike": "-4.5%",
      "Premio_Bruto": 0.1,
      "IR": 0.015,
      "Corretagem": 0.0059,
      "Premio_Liquido": 0.0791,
      "Taxa": 1.2822,
      "Taxa_Dia": 0.0493,
      "Taxa_Mes": 1.48,
      "Volume": 122400,
      "Bid_Volume": 12000,
      "Sem_Oferta": false,
      "Liquidez": "ALTA",
      "Score": 4.5,
      "CDI": "SUPERA",
      "Tipo": "PUT",
      "Estrategia": "Put Vendida",
      "Garantia_Por_Lote": 589,
      "Lotes_Possiveis": 127,
      "Garantia_Total": 74803,
      "Ganho_Total": 1004.7,
      "Limite_Put": 75000,
      "Pct_Limite_Usado": 99.7,
      "Delta": -0.204,
      "Gamma": 0.5903,
      "Theta": -0.0019,
      "Vega": 0.0056,
      "Rho": -0.0014,
      "Poe": 22.72,
      "Margin": 0,
      "IV": 31.33,
      "Moneyness": "OTM"
    },
    {
      "Acao": "VLID",
      "Preco_Atual": 18.15,
      "Preco_Medio": 21.57,
      "Quantidade": 1000,
      "Ticker_Opcao": "VLIDR168",
      "Estilo": "EUROPEAN",
      "Venc": "2026-06-19",
      "Dias_ate_Venc": 26,
      "Strike": 16.7,
      "Posicao": "OTM",
      "Dist_Strike": "-8.0%",
      "Premio_Bruto": 0.41,
      "IR": 0.0615,
      "Corretagem": 0.0167,
      "Premio_Liquido": 0.3318,
      "Taxa": 1.8281,
      "Taxa_Dia": 0.0703,
      "Taxa_Mes": 2.11,
      "Volume": 9100,
      "Bid_Volume": 0,
      "Sem_Oferta": true,
      "Liquidez": "ALTA",
      "Score": 4.5,
      "CDI": "SUPERA",
      "Tipo": "PUT",
      "Estrategia": "Put Vendida",
      "Garantia_Por_Lote": 1670,
      "Lotes_Possiveis": 44,
      "Garantia_Total": 73480,
      "Ganho_Total": 1459.92,
      "Limite_Put": 75000,
      "Pct_Limite_Usado": 98,
      "Delta": -0.142,
      "Gamma": 0.1292,
      "Theta": -0.006,
      "Vega": 0.0131,
      "Rho": -0.0028,
      "Poe": 16.52,
      "Margin": 0,
      "IV": 47.29,
      "Moneyness": "OTM"
    },
    {
      "Acao": "BBAS",
      "Preco_Atual": 21.54,
      "Preco_Medio": 22.58,
      "Quantidade": 1000,
      "Ticker_Opcao": "BBASR207W1",
      "Estilo": "EUROPEAN",
      "Venc": "2026-06-05",
      "Dias_ate_Venc": 16,
      "Strike": 20.76,
      "Posicao": "OTM",
      "Dist_Strike": "-3.6%",
      "Premio_Bruto": 0.35,
      "IR": 0.0525,
      "Corretagem": 0.0208,
      "Premio_Liquido": 0.2767,
      "Taxa": 1.2848,
      "Taxa_Dia": 0.0803,
      "Taxa_Mes": 2.41,
      "Volume": 100,
      "Bid_Volume": 0,
      "Sem_Oferta": true,
      "Liquidez": "ALTA",
      "Score": 4.5,
      "CDI": "SUPERA",
      "Tipo": "PUT",
      "Estrategia": "Put Vendida",
      "Garantia_Por_Lote": 2076,
      "Lotes_Possiveis": 36,
      "Garantia_Total": 74736,
      "Ganho_Total": 996.26,
      "Limite_Put": 75000,
      "Pct_Limite_Usado": 99.6,
      "Delta": -0.262,
      "Gamma": 0.1968,
      "Theta": -0.0134,
      "Vega": 0.0177,
      "Rho": -0.0038,
      "Poe": 28.74,
      "Margin": 0,
      "IV": 34.75,
      "Moneyness": "OTM"
    },
    {
      "Acao": "BBAS",
      "Preco_Atual": 21.54,
      "Preco_Medio": 22.58,
      "Quantidade": 1000,
      "Ticker_Opcao": "BBASR203",
      "Estilo": "EUROPEAN",
      "Venc": "2026-06-19",
      "Dias_ate_Venc": 26,
      "Strike": 20.35,
      "Posicao": "OTM",
      "Dist_Strike": "-5.5%",
      "Premio_Bruto": 0.33,
      "IR": 0.0495,
      "Corretagem": 0.0204,
      "Premio_Liquido": 0.2602,
      "Taxa": 1.2078,
      "Taxa_Dia": 0.0465,
      "Taxa_Mes": 1.39,
      "Volume": 112600,
      "Bid_Volume": 3000,
      "Sem_Oferta": false,
      "Liquidez": "ALTA",
      "Score": 4.5,
      "CDI": "SUPERA",
      "Tipo": "PUT",
      "Estrategia": "Put Vendida",
      "Garantia_Por_Lote": 2035,
      "Lotes_Possiveis": 36,
      "Garantia_Total": 73260,
      "Ganho_Total": 936.54,
      "Limite_Put": 75000,
      "Pct_Limite_Usado": 97.7,
      "Delta": -0.237,
      "Gamma": 0.1475,
      "Theta": -0.0094,
      "Vega": 0.0212,
      "Rho": -0.0056,
      "Poe": 26.87,
      "Margin": 0,
      "IV": 31.56,
      "Moneyness": "OTM"
    },
    {
      "Acao": "ITUB",
      "Preco_Atual": 40.33,
      "Preco_Medio": 44.54,
      "Quantidade": 500,
      "Ticker_Opcao": "ITUBR388W1",
      "Estilo": "EUROPEAN",
      "Venc": "2026-06-05",
      "Dias_ate_Venc": 16,
      "Strike": 38.86,
      "Posicao": "OTM",
      "Dist_Strike": "-3.6%",
      "Premio_Bruto": 0.5,
      "IR": 0.075,
      "Corretagem": 0.0389,
      "Premio_Liquido": 0.3861,
      "Taxa": 0.9575,
      "Taxa_Dia": 0.0598,
      "Taxa_Mes": 1.8,
      "Volume": 400,
      "Bid_Volume": 0,
      "Sem_Oferta": true,
      "Liquidez": "ALTA",
      "Score": 4.5,
      "CDI": "SUPERA",
      "Tipo": "PUT",
      "Estrategia": "Put Vendida",
      "Garantia_Por_Lote": 3886,
      "Lotes_Possiveis": 19,
      "Garantia_Total": 73834,
      "Ganho_Total": 733.67,
      "Limite_Put": 75000,
      "Pct_Limite_Usado": 98.4,
      "Delta": -0.288,
      "Gamma": 0.1314,
      "Theta": -0.0209,
      "Vega": 0.0343,
      "Rho": -0.0076,
      "Poe": 31.08,
      "Margin": 0,
      "IV": 26.32,
      "Moneyness": "OTM"
    },
    {
      "Acao": "ITUB",
      "Preco_Atual": 40.33,
      "Preco_Medio": 44.54,
      "Quantidade": 500,
      "Ticker_Opcao": "ITUBR393W1",
      "Estilo": "EUROPEAN",
      "Venc": "2026-06-05",
      "Dias_ate_Venc": 16,
      "Strike": 39.36,
      "Posicao": "OTM",
      "Dist_Strike": "-2.4%",
      "Premio_Bruto": 0.48,
      "IR": 0.072,
      "Corretagem": 0.0394,
      "Premio_Liquido": 0.3686,
      "Taxa": 0.9141,
      "Taxa_Dia": 0.0571,
      "Taxa_Mes": 1.71,
      "Volume": 100,
      "Bid_Volume": 0,
      "Sem_Oferta": true,
      "Liquidez": "ALTA",
      "Score": 4.5,
      "CDI": "SUPERA",
      "Tipo": "PUT",
      "Estrategia": "Put Vendida",
      "Garantia_Por_Lote": 3936,
      "Lotes_Possiveis": 19,
      "Garantia_Total": 74784,
      "Ganho_Total": 700.42,
      "Limite_Put": 75000,
      "Pct_Limite_Usado": 99.7,
      "Delta": -0.292,
      "Gamma": 0.1307,
      "Theta": -0.0212,
      "Vega": 0.0349,
      "Rho": -0.0078,
      "Poe": 31.52,
      "Margin": 0,
      "IV": 25.29,
      "Moneyness": "OTM"
    },
    {
      "Acao": "ITUB",
      "Preco_Atual": 40.33,
      "Preco_Medio": 44.54,
      "Quantidade": 500,
      "Ticker_Opcao": "ITUBR424",
      "Estilo": "EUROPEAN",
      "Venc": "2026-06-19",
      "Dias_ate_Venc": 26,
      "Strike": 38.63,
      "Posicao": "OTM",
      "Dist_Strike": "-4.2%",
      "Premio_Bruto": 0.51,
      "IR": 0.0765,
      "Corretagem": 0.0386,
      "Premio_Liquido": 0.3949,
      "Taxa": 0.9791,
      "Taxa_Dia": 0.0377,
      "Taxa_Mes": 1.13,
      "Volume": 66200,
      "Bid_Volume": 200,
      "Sem_Oferta": false,
      "Liquidez": "ALTA",
      "Score": 4.5,
      "CDI": "SUPERA",
      "Tipo": "PUT",
      "Estrategia": "Put Vendida",
      "Garantia_Por_Lote": 3863,
      "Lotes_Possiveis": 19,
      "Garantia_Total": 73397,
      "Ganho_Total": 750.25,
      "Limite_Put": 75000,
      "Pct_Limite_Usado": 97.9,
      "Delta": -0.23,
      "Gamma": 0.0906,
      "Theta": -0.014,
      "Vega": 0.0393,
      "Rho": -0.0101,
      "Poe": 25.6,
      "Margin": 0,
      "IV": 26.95,
      "Moneyness": "OTM"
    },
    {
      "Acao": "ITUB",
      "Preco_Atual": 40.33,
      "Preco_Medio": 44.54,
      "Quantidade": 500,
      "Ticker_Opcao": "ITUBR430",
      "Estilo": "EUROPEAN",
      "Venc": "2026-06-19",
      "Dias_ate_Venc": 26,
      "Strike": 38.87,
      "Posicao": "OTM",
      "Dist_Strike": "-3.6%",
      "Premio_Bruto": 0.57,
      "IR": 0.0855,
      "Corretagem": 0.0389,
      "Premio_Liquido": 0.4456,
      "Taxa": 1.105,
      "Taxa_Dia": 0.0425,
      "Taxa_Mes": 1.27,
      "Volume": 138726,
      "Bid_Volume": 200,
      "Sem_Oferta": false,
      "Liquidez": "ALTA",
      "Score": 4.5,
      "CDI": "SUPERA",
      "Tipo": "PUT",
      "Estrategia": "Put Vendida",
      "Garantia_Por_Lote": 3887,
      "Lotes_Possiveis": 19,
      "Garantia_Total": 73853,
      "Ganho_Total": 846.7,
      "Limite_Put": 75000,
      "Pct_Limite_Usado": 98.5,
      "Delta": -0.305,
      "Gamma": 0.1058,
      "Theta": -0.015,
      "Vega": 0.0448,
      "Rho": -0.0132,
      "Poe": 33.43,
      "Margin": 0,
      "IV": 23.55,
      "Moneyness": "OTM"
    },
    {
      "Acao": "CMIG",
      "Preco_Atual": 11.8,
      "Preco_Medio": 12.11,
      "Quantidade": 1200,
      "Ticker_Opcao": "CMIGF139",
      "Estilo": "AMERICAN",
      "Venc": "2026-06-19",
      "Dias_ate_Venc": 26,
      "Strike": 12.24,
      "Posicao": "OTM",
      "Dist_Strike": "+3.7%",
      "Premio_Bruto": 0.16,
      "IR": 0.024,
      "Corretagem": 0.0122,
      "Premio_Liquido": 0.1238,
      "Taxa": 1.0488,
      "Taxa_Dia": 0.0403,
      "Taxa_Mes": 1.21,
      "Volume": 79400,
      "Bid_Volume": 0,
      "Sem_Oferta": true,
      "Liquidez": "ALTA",
      "Score": 3.5,
      "CDI": "SUPERA",
      "Tipo": "CALL",
      "Estrategia": "Call Vendida",
      "Ganho_Por_Lote": 12.38,
      "Ganho_Total": 148.51,
      "Lotes_Carteira": 12,
      "Delta": 0.28,
      "Gamma": 0.3644,
      "Theta": -0.0077,
      "Vega": 0.0124,
      "Rho": 0.0032,
      "Poe": 25.39,
      "Margin": 0,
      "IV": 25.56,
      "Moneyness": "OTM"
    },
    {
      "Acao": "POMO",
      "Preco_Atual": 6.17,
      "Preco_Medio": 6.49,
      "Quantidade": 3200,
      "Ticker_Opcao": "POMOF666",
      "Estilo": "EUROPEAN",
      "Venc": "2026-06-19",
      "Dias_ate_Venc": 26,
      "Strike": 6.59,
      "Posicao": "OTM",
      "Dist_Strike": "+6.8%",
      "Premio_Bruto": 0.08,
      "IR": 0.012,
      "Corretagem": 0.0066,
      "Premio_Liquido": 0.0614,
      "Taxa": 0.9953,
      "Taxa_Dia": 0.0383,
      "Taxa_Mes": 1.15,
      "Volume": 36700,
      "Bid_Volume": 0,
      "Sem_Oferta": true,
      "Liquidez": "ALTA",
      "Score": 3.5,
      "CDI": "SUPERA",
      "Tipo": "CALL",
      "Estrategia": "Call Vendida",
      "Ganho_Por_Lote": 6.14,
      "Ganho_Total": 196.51,
      "Lotes_Carteira": 32,
      "Delta": 0.204,
      "Gamma": 0.6002,
      "Theta": -0.0033,
      "Vega": 0.0055,
      "Rho": 0.0012,
      "Poe": 18.31,
      "Margin": 0,
      "IV": 28.95,
      "Moneyness": "OTM"
    },
    {
      "Acao": "CMIG",
      "Preco_Atual": 11.8,
      "Preco_Medio": 12.11,
      "Quantidade": 1200,
      "Ticker_Opcao": "CMIGR129",
      "Estilo": "EUROPEAN",
      "Venc": "2026-06-19",
      "Dias_ate_Venc": 26,
      "Strike": 11.24,
      "Posicao": "OTM",
      "Dist_Strike": "-4.7%",
      "Premio_Bruto": 0.15,
      "IR": 0.0225,
      "Corretagem": 0.0112,
      "Premio_Liquido": 0.1163,
      "Taxa": 0.9853,
      "Taxa_Dia": 0.0379,
      "Taxa_Mes": 1.14,
      "Volume": 154400,
      "Bid_Volume": 0,
      "Sem_Oferta": true,
      "Liquidez": "ALTA",
      "Score": 3.5,
      "CDI": "SUPERA",
      "Tipo": "PUT",
      "Estrategia": "Put Vendida",
      "Garantia_Por_Lote": 1124,
      "Lotes_Possiveis": 66,
      "Garantia_Total": 74184,
      "Ganho_Total": 767.32,
      "Limite_Put": 75000,
      "Pct_Limite_Usado": 98.9,
      "Delta": -0.204,
      "Gamma": 0.2978,
      "Theta": -0.0037,
      "Vega": 0.0107,
      "Rho": -0.0026,
      "Poe": 22.74,
      "Margin": 0,
      "IV": 28.4,
      "Moneyness": "OTM"
    },
    {
      "Acao": "VLID",
      "Preco_Atual": 18.15,
      "Preco_Medio": 21.57,
      "Quantidade": 1000,
      "Ticker_Opcao": "VLIDR163",
      "Estilo": "EUROPEAN",
      "Venc": "2026-06-19",
      "Dias_ate_Venc": 26,
      "Strike": 16.2,
      "Posicao": "OTM",
      "Dist_Strike": "-10.7%",
      "Premio_Bruto": 0.26,
      "IR": 0.039,
      "Corretagem": 0.0162,
      "Premio_Liquido": 0.2048,
      "Taxa": 1.1284,
      "Taxa_Dia": 0.0434,
      "Taxa_Mes": 1.3,
      "Volume": 16200,
      "Bid_Volume": 0,
      "Sem_Oferta": true,
      "Liquidez": "ALTA",
      "Score": 3.5,
      "CDI": "SUPERA",
      "Tipo": "PUT",
      "Estrategia": "Put Vendida",
      "Garantia_Por_Lote": 1620,
      "Lotes_Possiveis": 46,
      "Garantia_Total": 74520,
      "Ganho_Total": 942.08,
      "Limite_Put": 75000,
      "Pct_Limite_Usado": 99.4,
      "Delta": -0.237,
      "Gamma": 0.1887,
      "Theta": -0.0073,
      "Vega": 0.0169,
      "Rho": -0.0044,
      "Poe": 26.75,
      "Margin": 0,
      "IV": 31.18,
      "Moneyness": "OTM"
    }
  ]
}